Workbook

Sheet 2025-11-19 to 11-25
A1: 2025-11-05 - Wednesday
A2: Recs:
A3: NVDA – NVIDIA Corporation
A4: AAPL – Apple Inc.
A5: MSFT – Microsoft Corporation
A6: ERICb.ST – Telefonaktiebolaget LM Ericsson B
A7: BOL – The Boliden Company
A8: Perf (prev recs):
A9: N/A
A10: N/A
A11: N/A
A12: N/A
... A529: S&P500 N/A

Sheet 2
A1: 2025-11-19 - Wednesday
A2: Recs:
A3: NVDA – NVIDIA Corp
A4: ERIC – Telefonaktiebolaget LM Ericsson
A5: VOLV-B.ST – AB Volvo (publ) B
A6: AZN.ST – AstraZeneca PLC
A7: VOLCAR-B.ST – Volvo Car AB (publ.)
A8: Perf (prev recs):
A9: N/A
A10: N/A
A11: N/A
A12: N/A
... A113: This automation has been paused due to too many unread executions. You can resume it in automations settings or by asking ChatGPT.

Sheet 3
A1: Recs:
A2: GEV - GE Vernova Inc (breakout after strong catalyst and technical momentum)Investors+1
A3: PLTR - Palantir Technologies (recent contract win and positive flow)Barron's
A4: SATS - EchoStar Corp (premarket strength and sector interest)Barron's
A5: AVTR - Avantor Inc (premarket gains signaling momentum)Barron's
A6: FSLR - First Solar (sector news on project supply momentum)Simply Wall St
A8: Prev days return S&P500 +0.67%investing.com
A10: 2025‑12‑12 / 08:15 - Friday
A12: Recs:
A13: NVDA - Nvidia (momentum from AI demand and trading strength)
A14: MSFT - Microsoft (strong cloud earnings sentiment driving flow)
A15: TSLA - Tesla (price breakout and volume spike)
... A52: Prev days return S&P500 -1.07

Sheet Sum and Cleaner
A1: String | B1: Is date? | C1: Date | D1: Rec 1 | E1: Rec 2 | F1: Rec 3 | G1: Rec 4 | H1: Rec 5
A2: 2025-11-05 - Wednesday | B2: =ISNUMBER(LEFT(A2,4)+1-1) -> TRUE | C2: =IF(B2,LEFT(A2,10),C1) -> 2025-11-05 | D2: =A4 -> NVDA – NVIDIA Corporation | E2: =A5 -> AAPL – Apple Inc. | F2: =A6 -> MSFT – Microsoft Corporation | G2: =A7 -> ERICb.ST – Telefonaktiebolaget LM Ericsson B | H2: =A8 -> BOL – The Boliden Company
A3: Recs: | B3: =ISNUMBER(LEFT(A3,4)+1-1) -> FALSE | C3: =IF(B3,LEFT(A3,10),C2) -> 2025-11-05 | D3: =A5 -> AAPL – Apple Inc. | E3: =A6 -> MSFT – Microsoft Corporation | F3: =A7 -> ERICb.ST – Telefonaktiebolaget LM Ericsson B | G3: =A8 -> BOL – The Boliden Company | H3: =A9 -> Perf (prev recs):
A4: NVDA – NVIDIA Corporation | B4: =ISNUMBER(LEFT(A4,4)+1-1) -> FALSE | C4: =IF(B4,LEFT(A4,10),C3) -> 2025-11-05 | D4: =A6 -> MSFT – Microsoft Corporation | E4: =A7 -> ERICb.ST – Telefonaktiebolaget LM Ericsson B | F4: =A8 -> BOL – The Boliden Company | G4: =A9 -> Perf (prev recs): | H4: =A10 -> N/A
A5: AAPL – Apple Inc. | B5: =ISNUMBER(LEFT(A5,4)+1-1) -> FALSE | C5: =IF(B5,LEFT(A5,10),C4) -> 2025-11-05 | D5: =A7 -> ERICb.ST – Telefonaktiebolaget LM Ericsson B | E5: =A8 -> BOL – The Boliden Company | F5: =A9 -> Perf (prev recs): | G5: =A10 -> N/A | H5: =A11 -> N/A
A6: MSFT – Microsoft Corporation | B6: =ISNUMBER(LEFT(A6,4)+1-1) -> FALSE | C6: =IF(B6,LEFT(A6,10),C5) -> 2025-11-05 | D6: =A8 -> BOL – The Boliden Company | E6: =A9 -> Perf (prev recs): | F6: =A10 -> N/A | G6: =A11 -> N/A | H6: =A12 -> N/A
A7: ERICb.ST – Telefonaktiebolaget LM Ericsson B | B7: =ISNUMBER(LEFT(A7,4)+1-1) -> FALSE | C7: =IF(B7,LEFT(A7,10),C6) -> 2025-11-05 | D7: =A9 -> Perf (prev recs): | E7: =A10 -> N/A | F7: =A11 -> N/A | G7: =A12 -> N/A | H7: =A13 -> N/A
A8: BOL – The Boliden Company | B8: =ISNUMBER(LEFT(A8,4)+1-1) -> FALSE | C8: =IF(B8,LEFT(A8,10),C7) -> 2025-11-05 | D8: =A10 -> N/A | E8: =A11 -> N/A | F8: =A12 -> N/A | G8: =A13 -> N/A | H8: =A14 -> N/A
A9: Perf (prev recs): | B9: =ISNUMBER(LEFT(A9,4)+1-1) -> FALSE | C9: =IF(B9,LEFT(A9,10),C8) -> 2025-11-05 | D9: =A11 -> N/A | E9: =A12 -> N/A | F9: =A13 -> N/A | G9: =A14 -> N/A | H9: =A15 -> Avg N/A
A10: N/A | B10: =ISNUMBER(LEFT(A10,4)+1-1) -> FALSE | C10: =IF(B10,LEFT(A10,10),C9) -> 2025-11-05 | D10: =A12 -> N/A | E10: =A13 -> N/A | F10: =A14 -> N/A | G10: =A15 -> Avg N/A | H10: =A16 -> S&P500 +X.XX%
A11: N/A | B11: =ISNUMBER(LEFT(A11,4)+1-1) -> FALSE | C11: =IF(B11,LEFT(A11,10),C10) -> 2025-11-05 | D11: =A13 -> N/A | E11: =A14 -> N/A | F11: =A15 -> Avg N/A | G11: =A16 -> S&P500 +X.XX% | H11: =A17 -> 0
A12: N/A | B12: =ISNUMBER(LEFT(A12,4)+1-1) -> FALSE | C12: =IF(B12,LEFT(A12,10),C11) -> 2025-11-05 | D12: =A14 -> N/A | E12: =A15 -> Avg N/A | F12: =A16 -> S&P500 +X.XX% | G12: =A17 -> 0 | H12: =A18 -> 2025-11-06 - Thursday
A13: N/A | B13: =ISNUMBER(LEFT(A13,4)+1-1) -> FALSE | C13: =IF(B13,LEFT(A13,10),C12) -> 2025-11-05 | D13: =A15 -> Avg N/A | E13: =A16 -> S&P500 +X.XX% | F13: =A17 -> 0 | G13: =A18 -> 2025-11-06 - Thursday | H13: =A19 -> Recs:
... A16: S&P500 +X.XX% | B16: =ISNUMBER(LEFT(A16,4)+1-1) -> FALSE | C16: =IF(B16,LEFT(A16,10),C15) -> 2025-11-05 | D16: =A18 -> 2025-11-06 - Thursday | E16: =A19 -> Recs: | F16: =A20 -> SECU-B.ST – Securitas AB | G16: =A21 -> ERIC-B.ST – Ericsson B | H16: =A22 -> TELIA.ST – Telia Company
B17: =ISNUMBER(LEFT(A17,4)+1-1) -> FALSE | C17: =IF(B17,LEFT(A17,10),C16) -> 2025-11-05 | D17: =A19 -> Recs: | E17: =A20 -> SECU-B.ST – Securitas AB | F17: =A21 -> ERIC-B.ST – Ericsson B | G17: =A22 -> TELIA.ST – Telia Company | H17: =A23 -> SAAB-B.ST – Saab AB
A18: 2025-11-06 - Thursday | B18: =ISNUMBER(LEFT(A18,4)+1-1) -> TRUE | C18: =IF(B18,LEFT(A18,10),C17) -> 2025-11-06 | D18: =A20 -> SECU-B.ST – Securitas AB | E18: =A21 -> ERIC-B.ST – Ericsson B | F18: =A22 -> TELIA.ST – Telia Company | G18: =A23 -> SAAB-B.ST – Saab AB | H18: =A24 -> VOLV-B.ST – AB Volvo B
A19: Recs: | B19: =ISNUMBER(LEFT(A19,4)+1-1) -> FALSE | C19: =IF(B19,LEFT(A19,10),C18) -> 2025-11-06 | D19: =A21 -> ERIC-B.ST – Ericsson B | E19: =A22 -> TELIA.ST – Telia Company | F19: =A23 -> SAAB-B.ST – Saab AB | G19: =A24 -> VOLV-B.ST – AB Volvo B | H19: =A25 -> Perf (prev recs):
A20: SECU-B.ST – Securitas AB | B20: =ISNUMBER(LEFT(A20,4)+1-1) -> FALSE | C20: =IF(B20,LEFT(A20,10),C19) -> 2025-11-06 | D20: =A22 -> TELIA.ST – Telia Company | E20: =A23 -> SAAB-B.ST – Saab AB | F20: =A24 -> VOLV-B.ST – AB Volvo B | G20: =A25 -> Perf (prev recs): | H20: =A26 -> N/A
A21: ERIC-B.ST – Ericsson B | B21: =ISNUMBER(LEFT(A21,4)+1-1) -> FALSE | C21: =IF(B21,LEFT(A21,10),C20) -> 2025-11-06 | D21: =A23 -> SAAB-B.ST – Saab AB | E21: =A24 -> VOLV-B.ST – AB Volvo B | F21: =A25 -> Perf (prev recs): | G21: =A26 -> N/A | H21: =A27 -> 0
A22: TELIA.ST – Telia Company | B22: =ISNUMBER(LEFT(A22,4)+1-1) -> FALSE | C22: =IF(B22,LEFT(A22,10),C21) -> 2025-11-06 | D22: =A24 -> VOLV-B.ST – AB Volvo B | E22: =A25 -> Perf (prev recs): | F22: =A26 -> N/A | G22: =A27 -> 0 | H22: =A28 -> 2025-11-07 - Friday
A23: SAAB-B.ST – Saab AB | B23: =ISNUMBER(LEFT(A23,4)+1-1) -> FALSE | C23: =IF(B23,LEFT(A23,10),C22) -> 2025-11-06 | D23: =A25 -> Perf (prev recs): | E23: =A26 -> N/A | F23: =A27 -> 0 | G23: =A28 -> 2025-11-07 - Friday | H23: =A29 -> Recs:
A24: VOLV-B.ST – AB Volvo B | B24: =ISNUMBER(LEFT(A24,4)+1-1) -> FALSE | C24: =IF(B24,LEFT(A24,10),C23) -> 2025-11-06 | D24: =A26 -> N/A | E24: =A27 -> 0 | F24: =A28 -> 2025-11-07 - Friday | G24: =A29 -> Recs: | H24: =A30 -> TELIA.ST – Telia Company
A25: Perf (prev recs): | B25: =ISNUMBER(LEFT(A25,4)+1-1) -> FALSE | C25: =IF(B25,LEFT(A25,10),C24) -> 2025-11-06 | D25: =A27 -> 0 | E25: =A28 -> 2025-11-07 - Friday | F25: =A29 -> Recs: | G25: =A30 -> TELIA.ST – Telia Company | H25: =A31 -> ERIC-B.ST – Ericsson B
A26: N/A | B26: =ISNUMBER(LEFT(A26,4)+1-1) -> FALSE | C26: =IF(B26,LEFT(A26,10),C25) -> 2025-11-06 | D26: =A28 -> 2025-11-07 - Friday | E26: =A29 -> Recs: | F26: =A30 -> TELIA.ST – Telia Company | G26: =A31 -> ERIC-B.ST – Ericsson B | H26: =A32 -> SAAB-B.ST – Saab AB
B27: =ISNUMBER(LEFT(A27,4)+1-1) -> FALSE | C27: =IF(B27,LEFT(A27,10),C26) -> 2025-11-06 | D27: =A29 -> Recs: | E27: =A30 -> TELIA.ST – Telia Company | F27: =A31 -> ERIC-B.ST – Ericsson B | G27: =A32 -> SAAB-B.ST – Saab AB | H27: =A33 -> VOLV-B.ST – AB Volvo B
A28: 2025-11-07 - Friday | B28: =ISNUMBER(LEFT(A28,4)+1-1) -> TRUE | C28: =IF(B28,LEFT(A28,10),C27) -> 2025-11-07 | D28: =A30 -> TELIA.ST – Telia Company | E28: =A31 -> ERIC-B.ST – Ericsson B | F28: =A32 -> SAAB-B.ST – Saab AB | G28: =A33 -> VOLV-B.ST – AB Volvo B | H28: =A34 -> NOK – Nokia Corporation
A29: Recs: | B29: =ISNUMBER(LEFT(A29,4)+1-1) -> FALSE | C29: =IF(B29,LEFT(A29,10),C28) -> 2025-11-07 | D29: =A31 -> ERIC-B.ST – Ericsson B | E29: =A32 -> SAAB-B.ST – Saab AB | F29: =A33 -> VOLV-B.ST – AB Volvo B | G29: =A34 -> NOK – Nokia Corporation | H29: =A35 -> Perf (prev recs):
A30: TELIA.ST – Telia Company | B30: =ISNUMBER(LEFT(A30,4)+1-1) -> FALSE | C30: =IF(B30,LEFT(A30,10),C29) -> 2025-11-07 | D30: =A32 -> SAAB-B.ST – Saab AB | E30: =A33 -> VOLV-B.ST – AB Volvo B | F30: =A34 -> NOK – Nokia Corporation | G30: =A35 -> Perf (prev recs): | H30: =A36 -> SECU-B.ST N/A
A31: ERIC-B.ST – Ericsson B | B31: =ISNUMBER(LEFT(A31,4)+1-1) -> FALSE | C31: =IF(B31,LEFT(A31,10),C30) -> 2025-11-07 | D31: =A33 -> VOLV-B.ST – AB Volvo B | E31: =A34 -> NOK – Nokia Corporation | F31: =A35 -> Perf (prev recs): | G31: =A36 -> SECU-B.ST N/A | H31: =A37 -> TELIA.ST N/A
A32: SAAB-B.ST – Saab AB | B32: =ISNUMBER(LEFT(A32,4)+1-1) -> FALSE | C32: =IF(B32,LEFT(A32,10),C31) -> 2025-11-07 | D32: =A34 -> NOK – Nokia Corporation | E32: =A35 -> Perf (prev recs): | F32: =A36 -> SECU-B.ST N/A | G32: =A37 -> TELIA.ST N/A | H32: =A38 -> SAAB-B.ST N/A
A33: VOLV-B.ST – AB Volvo B | B33: =ISNUMBER(LEFT(A33,4)+1-1) -> FALSE | C33: =IF(B33,LEFT(A33,10),C32) -> 2025-11-07 | D33: =A35 -> Perf (prev recs): | E33: =A36 -> SECU-B.ST N/A | F33: =A37 -> TELIA.ST N/A | G33: =A38 -> SAAB-B.ST N/A | H33: =A39 -> VOLV-B.ST N/A
A34: NOK – Nokia Corporation | B34: =ISNUMBER(LEFT(A34,4)+1-1) -> FALSE | C34: =IF(B34,LEFT(A34,10),C33) -> 2025-11-07 | D34: =A36 -> SECU-B.ST N/A | E34: =A37 -> TELIA.ST N/A | F34: =A38 -> SAAB-B.ST N/A | G34: =A39 -> VOLV-B.ST N/A | H34: =A40 -> ERIC-B.ST N/A
A35: Perf (prev recs): | B35: =ISNUMBER(LEFT(A35,4)+1-1) -> FALSE | C35: =IF(B35,LEFT(A35,10),C34) -> 2025-11-07 | D35: =A37 -> TELIA.ST N/A | E35: =A38 -> SAAB-B.ST N/A | F35: =A39 -> VOLV-B.ST N/A | G35: =A40 -> ERIC-B.ST N/A | H35: =A41 -> Avg N/A
A36: SECU-B.ST N/A | B36: =ISNUMBER(LEFT(A36,4)+1-1) -> FALSE | C36: =IF(B36,LEFT(A36,10),C35) -> 2025-11-07 | D36: =A38 -> SAAB-B.ST N/A | E36: =A39 -> VOLV-B.ST N/A | F36: =A40 -> ERIC-B.ST N/A | G36: =A41 -> Avg N/A | H36: =A42 -> S&P500 N/A
A37: TELIA.ST N/A | B37: =ISNUMBER(LEFT(A37,4)+1-1) -> FALSE | C37: =IF(B37,LEFT(A37,10),C36) -> 2025-11-07 | D37: =A39 -> VOLV-B.ST N/A | E37: =A40 -> ERIC-B.ST N/A | F37: =A41 -> Avg N/A | G37: =A42 -> S&P500 N/A | H37: =A43 -> 0
A38: SAAB-B.ST N/A | B38: =ISNUMBER(LEFT(A38,4)+1-1) -> FALSE | C38: =IF(B38,LEFT(A38,10),C37) -> 2025-11-07 | D38: =A40 -> ERIC-B.ST N/A | E38: =A41 -> Avg N/A | F38: =A42 -> S&P500 N/A | G38: =A43 -> 0 | H38: =A44 -> 2025-11-08 - Saturday
A39: VOLV-B.ST N/A | B39: =ISNUMBER(LEFT(A39,4)+1-1) -> FALSE | C39: =IF(B39,LEFT(A39,10),C38) -> 2025-11-07 | D39: =A41 -> Avg N/A | E39: =A42 -> S&P500 N/A | F39: =A43 -> 0 | G39: =A44 -> 2025-11-08 - Saturday | H39: =A45 -> Recs:
... A42: S&P500 N/A | B42: =ISNUMBER(LEFT(A42,4)+1-1) -> FALSE | C42: =IF(B42,LEFT(A42,10),C41) -> 2025-11-07 | D42: =A44 -> 2025-11-08 - Saturday | E42: =A45 -> Recs: | F42: =A46 -> SWEC-B.ST – Sweco AB | G42: =A47 -> ATCO-A.ST – Atlas Copco A | H42: =A48 -> HEXA-B.ST – Hexagon AB
B43: =ISNUMBER(LEFT(A43,4)+1-1) -> FALSE | C43: =IF(B43,LEFT(A43,10),C42) -> 2025-11-07 | D43: =A45 -> Recs: | E43: =A46 -> SWEC-B.ST – Sweco AB | F43: =A47 -> ATCO-A.ST – Atlas Copco A | G43: =A48 -> HEXA-B.ST – Hexagon AB | H43: =A49 -> INVE-B.ST – Investor AB
A44: 2025-11-08 - Saturday | B44: =ISNUMBER(LEFT(A44,4)+1-1) -> TRUE | C44: =IF(B44,LEFT(A44,10),C43) -> 2025-11-08 | D44: =A46 -> SWEC-B.ST – Sweco AB | E44: =A47 -> ATCO-A.ST – Atlas Copco A | F44: =A48 -> HEXA-B.ST – Hexagon AB | G44: =A49 -> INVE-B.ST – Investor AB | H44: =A50 -> SAND.ST – Sandvik AB
A45: Recs: | B45: =ISNUMBER(LEFT(A45,4)+1-1) -> FALSE | C45: =IF(B45,LEFT(A45,10),C44) -> 2025-11-08 | D45: =A47 -> ATCO-A.ST – Atlas Copco A | E45: =A48 -> HEXA-B.ST – Hexagon AB | F45: =A49 -> INVE-B.ST – Investor AB | G45: =A50 -> SAND.ST – Sandvik AB | H45: =A51 -> Perf (prev recs):
A46: SWEC-B.ST – Sweco AB | B46: =ISNUMBER(LEFT(A46,4)+1-1) -> FALSE | C46: =IF(B46,LEFT(A46,10),C45) -> 2025-11-08 | D46: =A48 -> HEXA-B.ST – Hexagon AB | E46: =A49 -> INVE-B.ST – Investor AB | F46: =A50 -> SAND.ST – Sandvik AB | G46: =A51 -> Perf (prev recs): | H46: =A52 -> TELIA.ST N/A
A47: ATCO-A.ST – Atlas Copco A | B47: =ISNUMBER(LEFT(A47,4)+1-1) -> FALSE | C47: =IF(B47,LEFT(A47,10),C46) -> 2025-11-08 | D47: =A49 -> INVE-B.ST – Investor AB | E47: =A50 -> SAND.ST – Sandvik AB | F47: =A51 -> Perf (prev recs): | G47: =A52 -> TELIA.ST N/A | H47: =A53 -> ERIC-B.ST N/A
A48: HEXA-B.ST – Hexagon AB | B48: =ISNUMBER(LEFT(A48,4)+1-1) -> FALSE | C48: =IF(B48,LEFT(A48,10),C47) -> 2025-11-08 | D48: =A50 -> SAND.ST – Sandvik AB | E48: =A51 -> Perf (prev recs): | F48: =A52 -> TELIA.ST N/A | G48: =A53 -> ERIC-B.ST N/A | H48: =A54 -> SAAB-B.ST N/A
A49: INVE-B.ST – Investor AB | B49: =ISNUMBER(LEFT(A49,4)+1-1) -> FALSE | C49: =IF(B49,LEFT(A49,10),C48) -> 2025-11-08 | D49: =A51 -> Perf (prev recs): | E49: =A52 -> TELIA.ST N/A | F49: =A53 -> ERIC-B.ST N/A | G49: =A54 -> SAAB-B.ST N/A | H49: =A55 -> VOLV-B.ST N/A
A50: SAND.ST – Sandvik AB | B50: =ISNUMBER(LEFT(A50,4)+1-1) -> FALSE | C50: =IF(B50,LEFT(A50,10),C49) -> 2025-11-08 | D50: =A52 -> TELIA.ST N/A | E50: =A53 -> ERIC-B.ST N/A | F50: =A54 -> SAAB-B.ST N/A | G50: =A55 -> VOLV-B.ST N/A | H50: =A56 -> NOK N/A
A51: Perf (prev recs): | B51: =ISNUMBER(LEFT(A51,4)+1-1) -> FALSE | C51: =IF(B51,LEFT(A51,10),C50) -> 2025-11-08 | D51: =A53 -> ERIC-B.ST N/A | E51: =A54 -> SAAB-B.ST N/A | F51: =A55 -> VOLV-B.ST N/A | G51: =A56 -> NOK N/A | H51: =A57 -> Avg N/A
A52: TELIA.ST N/A | B52: =ISNUMBER(LEFT(A52,4)+1-1) -> FALSE | C52: =IF(B52,LEFT(A52,10),C51) -> 2025-11-08 | D52: =A54 -> SAAB-B.ST N/A | E52: =A55 -> VOLV-B.ST N/A | F52: =A56 -> NOK N/A | G52: =A57 -> Avg N/A | H52: =A58 -> S&P500 N/A
A53: ERIC-B.ST N/A | B53: =ISNUMBER(LEFT(A53,4)+1-1) -> FALSE | C53: =IF(B53,LEFT(A53,10),C52) -> 2025-11-08 | D53: =A55 -> VOLV-B.ST N/A | E53: =A56 -> NOK N/A | F53: =A57 -> Avg N/A | G53: =A58 -> S&P500 N/A | H53: =A59 -> 0
A54: SAAB-B.ST N/A | B54: =ISNUMBER(LEFT(A54,4)+1-1) -> FALSE | C54: =IF(B54,LEFT(A54,10),C53) -> 2025-11-08 | D54: =A56 -> NOK N/A | E54: =A57 -> Avg N/A | F54: =A58 -> S&P500 N/A | G54: =A59 -> 0 | H54: =A60 -> 2025-11-09 - Sunday
A55: VOLV-B.ST N/A | B55: =ISNUMBER(LEFT(A55,4)+1-1) -> FALSE | C55: =IF(B55,LEFT(A55,10),C54) -> 2025-11-08 | D55: =A57 -> Avg N/A | E55: =A58 -> S&P500 N/A | F55: =A59 -> 0 | G55: =A60 -> 2025-11-09 - Sunday | H55: =A61 -> Recs:
... A58: S&P500 N/A | B58: =ISNUMBER(LEFT(A58,4)+1-1) -> FALSE | C58: =IF(B58,LEFT(A58,10),C57) -> 2025-11-08 | D58: =A60 -> 2025-11-09 - Sunday | E58: =A61 -> Recs: | F58: =A62 -> SWEC-B.ST – Sweco AB | G58: =A63 -> ERIC-B.ST – Ericsson AB B | H58: =A64 -> SSAB-B.ST – SSAB AB B
B59: =ISNUMBER(LEFT(A59,4)+1-1) -> FALSE | C59: =IF(B59,LEFT(A59,10),C58) -> 2025-11-08 | D59: =A61 -> Recs: | E59: =A62 -> SWEC-B.ST – Sweco AB | F59: =A63 -> ERIC-B.ST – Ericsson AB B | G59: =A64 -> SSAB-B.ST – SSAB AB B | H59: =A65 -> SHBa.ST – Handelsbanken AB
A60: 2025-11-09 - Sunday | B60: =ISNUMBER(LEFT(A60,4)+1-1) -> TRUE | C60: =IF(B60,LEFT(A60,10),C59) -> 2025-11-09 | D60: =A62 -> SWEC-B.ST – Sweco AB | E60: =A63 -> ERIC-B.ST – Ericsson AB B | F60: =A64 -> SSAB-B.ST – SSAB AB B | G60: =A65 -> SHBa.ST – Handelsbanken AB | H60: =A66 -> INVE-B.ST – Investor AB B
A61: Recs: | B61: =ISNUMBER(LEFT(A61,4)+1-1) -> FALSE | C61: =IF(B61,LEFT(A61,10),C60) -> 2025-11-09 | D61: =A63 -> ERIC-B.ST – Ericsson AB B | E61: =A64 -> SSAB-B.ST – SSAB AB B | F61: =A65 -> SHBa.ST – Handelsbanken AB | G61: =A66 -> INVE-B.ST – Investor AB B | H61: =A67 -> Perf (prev recs):
A62: SWEC-B.ST – Sweco AB | B62: =ISNUMBER(LEFT(A62,4)+1-1) -> FALSE | C62: =IF(B62,LEFT(A62,10),C61) -> 2025-11-09 | D62: =A64 -> SSAB-B.ST – SSAB AB B | E62: =A65 -> SHBa.ST – Handelsbanken AB | F62: =A66 -> INVE-B.ST – Investor AB B | G62: =A67 -> Perf (prev recs): | H62: =A68 -> TELIA.ST N/A
A63: ERIC-B.ST – Ericsson AB B | B63: =ISNUMBER(LEFT(A63,4)+1-1) -> FALSE | C63: =IF(B63,LEFT(A63,10),C62) -> 2025-11-09 | D63: =A65 -> SHBa.ST – Handelsbanken AB | E63: =A66 -> INVE-B.ST – Investor AB B | F63: =A67 -> Perf (prev recs): | G63: =A68 -> TELIA.ST N/A | H63: =A69 -> ERIC-B.ST N/A
A64: SSAB-B.ST – SSAB AB B | B64: =ISNUMBER(LEFT(A64,4)+1-1) -> FALSE | C64: =IF(B64,LEFT(A64,10),C63) -> 2025-11-09 | D64: =A66 -> INVE-B.ST – Investor AB B | E64: =A67 -> Perf (prev recs): | F64: =A68 -> TELIA.ST N/A | G64: =A69 -> ERIC-B.ST N/A | H64: =A70 -> SAAB-B.ST N/A
A65: SHBa.ST – Handelsbanken AB | B65: =ISNUMBER(LEFT(A65,4)+1-1) -> FALSE | C65: =IF(B65,LEFT(A65,10),C64) -> 2025-11-09 | D65: =A67 -> Perf (prev recs): | E65: =A68 -> TELIA.ST N/A | F65: =A69 -> ERIC-B.ST N/A | G65: =A70 -> SAAB-B.ST N/A | H65: =A71 -> VOLV-B.ST N/A
A66: INVE-B.ST – Investor AB B | B66: =ISNUMBER(LEFT(A66,4)+1-1) -> FALSE | C66: =IF(B66,LEFT(A66,10),C65) -> 2025-11-09 | D66: =A68 -> TELIA.ST N/A | E66: =A69 -> ERIC-B.ST N/A | F66: =A70 -> SAAB-B.ST N/A | G66: =A71 -> VOLV-B.ST N/A | H66: =A72 -> NOK N/A
A67: Perf (prev recs): | B67: =ISNUMBER(LEFT(A67,4)+1-1) -> FALSE | C67: =IF(B67,LEFT(A67,10),C66) -> 2025-11-09 | D67: =A69 -> ERIC-B.ST N/A | E67: =A70 -> SAAB-B.ST N/A | F67: =A71 -> VOLV-B.ST N/A | G67: =A72 -> NOK N/A | H67: =A73 -> Avg N/A
A68: TELIA.ST N/A | B68: =ISNUMBER(LEFT(A68,4)+1-1) -> FALSE | C68: =IF(B68,LEFT(A68,10),C67) -> 2025-11-09 | D68: =A70 -> SAAB-B.ST N/A | E68: =A71 -> VOLV-B.ST N/A | F68: =A72 -> NOK N/A | G68: =A73 -> Avg N/A | H68: =A74 -> S&P500 N/A
A69: ERIC-B.ST N/A | B69: =ISNUMBER(LEFT(A69,4)+1-1) -> FALSE | C69: =IF(B69,LEFT(A69,10),C68) -> 2025-11-09 | D69: =A71 -> VOLV-B.ST N/A | E69: =A72 -> NOK N/A | F69: =A73 -> Avg N/A | G69: =A74 -> S&P500 N/A | H69: =A75 -> 0
A70: SAAB-B.ST N/A | B70: =ISNUMBER(LEFT(A70,4)+1-1) -> FALSE | C70: =IF(B70,LEFT(A70,10),C69) -> 2025-11-09 | D70: =A72 -> NOK N/A | E70: =A73 -> Avg N/A | F70: =A74 -> S&P500 N/A | G70: =A75 -> 0 | H70: =A76 -> 2025-11-10 - Monday
A71: VOLV-B.ST N/A | B71: =ISNUMBER(LEFT(A71,4)+1-1) -> FALSE | C71: =IF(B71,LEFT(A71,10),C70) -> 2025-11-09 | D71: =A73 -> Avg N/A | E71: =A74 -> S&P500 N/A | F71: =A75 -> 0 | G71: =A76 -> 2025-11-10 - Monday | H71: =A77 -> Recs:
... A74: S&P500 N/A | B74: =ISNUMBER(LEFT(A74,4)+1-1) -> FALSE | C74: =IF(B74,LEFT(A74,10),C73) -> 2025-11-09 | D74: =A76 -> 2025-11-10 - Monday | E74: =A77 -> Recs: | F74: =A78 -> HEXA‑B.ST – Hexagon AB | G74: =A79 -> AZN – AstraZeneca plc | H74: =A80 -> EQTAB.ST – EQT AB
B75: =ISNUMBER(LEFT(A75,4)+1-1) -> FALSE | C75: =IF(B75,LEFT(A75,10),C74) -> 2025-11-09 | D75: =A77 -> Recs: | E75: =A78 -> HEXA‑B.ST – Hexagon AB | F75: =A79 -> AZN – AstraZeneca plc | G75: =A80 -> EQTAB.ST – EQT AB | H75: =A81 -> SAABb.ST – Saab AB B
A76: 2025-11-10 - Monday | B76: =ISNUMBER(LEFT(A76,4)+1-1) -> TRUE | C76: =IF(B76,LEFT(A76,10),C75) -> 2025-11-10 | D76: =A78 -> HEXA‑B.ST – Hexagon AB | E76: =A79 -> AZN – AstraZeneca plc | F76: =A80 -> EQTAB.ST – EQT AB | G76: =A81 -> SAABb.ST – Saab AB B | H76: =A82 -> BOL.ST – Boliden AB B
A77: Recs: | B77: =ISNUMBER(LEFT(A77,4)+1-1) -> FALSE | C77: =IF(B77,LEFT(A77,10),C76) -> 2025-11-10 | D77: =A79 -> AZN – AstraZeneca plc | E77: =A80 -> EQTAB.ST – EQT AB | F77: =A81 -> SAABb.ST – Saab AB B | G77: =A82 -> BOL.ST – Boliden AB B | H77: =A83 -> Perf (prev recs):
A78: HEXA‑B.ST – Hexagon AB | B78: =ISNUMBER(LEFT(A78,4)+1-1) -> FALSE | C78: =IF(B78,LEFT(A78,10),C77) -> 2025-11-10 | D78: =A80 -> EQTAB.ST – EQT AB | E78: =A81 -> SAABb.ST – Saab AB B | F78: =A82 -> BOL.ST – Boliden AB B | G78: =A83 -> Perf (prev recs): | H78: =A84 -> SWEC‑B.ST N/A
A79: AZN – AstraZeneca plc | B79: =ISNUMBER(LEFT(A79,4)+1-1) -> FALSE | C79: =IF(B79,LEFT(A79,10),C78) -> 2025-11-10 | D79: =A81 -> SAABb.ST – Saab AB B | E79: =A82 -> BOL.ST – Boliden AB B | F79: =A83 -> Perf (prev recs): | G79: =A84 -> SWEC‑B.ST N/A | H79: =A85 -> ATCO‑A.ST N/A
A80: EQTAB.ST – EQT AB | B80: =ISNUMBER(LEFT(A80,4)+1-1) -> FALSE | C80: =IF(B80,LEFT(A80,10),C79) -> 2025-11-10 | D80: =A82 -> BOL.ST – Boliden AB B | E80: =A83 -> Perf (prev recs): | F80: =A84 -> SWEC‑B.ST N/A | G80: =A85 -> ATCO‑A.ST N/A | H80: =A86 -> HEXA‑B.ST N/A
A81: SAABb.ST – Saab AB B | B81: =ISNUMBER(LEFT(A81,4)+1-1) -> FALSE | C81: =IF(B81,LEFT(A81,10),C80) -> 2025-11-10 | D81: =A83 -> Perf (prev recs): | E81: =A84 -> SWEC‑B.ST N/A | F81: =A85 -> ATCO‑A.ST N/A | G81: =A86 -> HEXA‑B.ST N/A | H81: =A87 -> INVE‑B.ST N/A
A82: BOL.ST – Boliden AB B | B82: =ISNUMBER(LEFT(A82,4)+1-1) -> FALSE | C82: =IF(B82,LEFT(A82,10),C81) -> 2025-11-10 | D82: =A84 -> SWEC‑B.ST N/A | E82: =A85 -> ATCO‑A.ST N/A | F82: =A86 -> HEXA‑B.ST N/A | G82: =A87 -> INVE‑B.ST N/A | H82: =A88 -> SAND.ST N/A
A83: Perf (prev recs): | B83: =ISNUMBER(LEFT(A83,4)+1-1) -> FALSE | C83: =IF(B83,LEFT(A83,10),C82) -> 2025-11-10 | D83: =A85 -> ATCO‑A.ST N/A | E83: =A86 -> HEXA‑B.ST N/A | F83: =A87 -> INVE‑B.ST N/A | G83: =A88 -> SAND.ST N/A | H83: =A89 -> Avg N/A
A84: SWEC‑B.ST N/A | B84: =ISNUMBER(LEFT(A84,4)+1-1) -> FALSE | C84: =IF(B84,LEFT(A84,10),C83) -> 2025-11-10 | D84: =A86 -> HEXA‑B.ST N/A | E84: =A87 -> INVE‑B.ST N/A | F84: =A88 -> SAND.ST N/A | G84: =A89 -> Avg N/A | H84: =A90 -> S&P500 N/A
A85: ATCO‑A.ST N/A | B85: =ISNUMBER(LEFT(A85,4)+1-1) -> FALSE | C85: =IF(B85,LEFT(A85,10),C84) -> 2025-11-10 | D85: =A87 -> INVE‑B.ST N/A | E85: =A88 -> SAND.ST N/A | F85: =A89 -> Avg N/A | G85: =A90 -> S&P500 N/A | H85: =A91 -> 2025-10-23 - Thursday
A86: HEXA‑B.ST N/A | B86: =ISNUMBER(LEFT(A86,4)+1-1) -> FALSE | C86: =IF(B86,LEFT(A86,10),C85) -> 2025-11-10 | D86: =A88 -> SAND.ST N/A | E86: =A89 -> Avg N/A | F86: =A90 -> S&P500 N/A | G86: =A91 -> 2025-10-23 - Thursday | H86: =A92 -> Recs:
A87: INVE‑B.ST N/A | B87: =ISNUMBER(LEFT(A87,4)+1-1) -> FALSE | C87: =IF(B87,LEFT(A87,10),C86) -> 2025-11-10 | D87: =A89 -> Avg N/A | E87: =A90 -> S&P500 N/A | F87: =A91 -> 2025-10-23 - Thursday | G87: =A92 -> Recs: | H87: =A93 -> TSLA – Tesla Inc
... A105: S&P500 +? | B105: =ISNUMBER(LEFT(A105,4)+1-1) -> FALSE | C105: =IF(B105,LEFT(A105,10),C104) -> 2025-10-23 | D105: =A107 -> 2025-10-24 - Friday | E105: =A108 -> Recs: | F105: =A109 -> TELIA – Telia Company AB | G105: =A110 -> PCELL – PowerCell Sweden AB | H105: =A111 -> SEB_A – SEB AB
B106: =ISNUMBER(LEFT(A106,4)+1-1) -> FALSE | C106: =IF(B106,LEFT(A106,10),C105) -> 2025-10-23 | D106: =A108 -> Recs: | E106: =A109 -> TELIA – Telia Company AB | F106: =A110 -> PCELL – PowerCell Sweden AB | G106: =A111 -> SEB_A – SEB AB | H106: =A112 -> ERIC – Ericsson AB
A107: 2025-10-24 - Friday | B107: =ISNUMBER(LEFT(A107,4)+1-1) -> TRUE | C107: =IF(B107,LEFT(A107,10),C106) -> 2025-10-24 | D107: =A109 -> TELIA – Telia Company AB | E107: =A110 -> PCELL – PowerCell Sweden AB | F107: =A111 -> SEB_A – SEB AB | G107: =A112 -> ERIC – Ericsson AB | H107: =A113 -> VOLV B – Volvo AB
A108: Recs: | B108: =ISNUMBER(LEFT(A108,4)+1-1) -> FALSE | C108: =IF(B108,LEFT(A108,10),C107) -> 2025-10-24 | D108: =A110 -> PCELL – PowerCell Sweden AB | E108: =A111 -> SEB_A – SEB AB | F108: =A112 -> ERIC – Ericsson AB | G108: =A113 -> VOLV B – Volvo AB | H108: =A114 -> Perf (prev recs):
A109: TELIA – Telia Company AB | B109: =ISNUMBER(LEFT(A109,4)+1-1) -> FALSE | C109: =IF(B109,LEFT(A109,10),C108) -> 2025-10-24 | D109: =A111 -> SEB_A – SEB AB | E109: =A112 -> ERIC – Ericsson AB | F109: =A113 -> VOLV B – Volvo AB | G109: =A114 -> Perf (prev recs): | H109: =A115 -> SKF‑B +0.79%
A110: PCELL – PowerCell Sweden AB | B110: =ISNUMBER(LEFT(A110,4)+1-1) -> FALSE | C110: =IF(B110,LEFT(A110,10),C109) -> 2025-10-24 | D110: =A112 -> ERIC – Ericsson AB | E110: =A113 -> VOLV B – Volvo AB | F110: =A114 -> Perf (prev recs): | G110: =A115 -> SKF‑B +0.79% | H110: =A116 -> NIBE B +0.75%
A111: SEB_A – SEB AB | B111: =ISNUMBER(LEFT(A111,4)+1-1) -> FALSE | C111: =IF(B111,LEFT(A111,10),C110) -> 2025-10-24 | D111: =A113 -> VOLV B – Volvo AB | E111: =A114 -> Perf (prev recs): | F111: =A115 -> SKF‑B +0.79% | G111: =A116 -> NIBE B +0.75% | H111: =A117 -> Addtech AB B +3.87%
A112: ERIC – Ericsson AB | B112: =ISNUMBER(LEFT(A112,4)+1-1) -> FALSE | C112: =IF(B112,LEFT(A112,10),C111) -> 2025-10-24 | D112: =A114 -> Perf (prev recs): | E112: =A115 -> SKF‑B +0.79% | F112: =A116 -> NIBE B +0.75% | G112: =A117 -> Addtech AB B +3.87% | H112: =A118 -> Trelleborg AB B +0.47%
A113: VOLV B – Volvo AB | B113: =ISNUMBER(LEFT(A113,4)+1-1) -> FALSE | C113: =IF(B113,LEFT(A113,10),C112) -> 2025-10-24 | D113: =A115 -> SKF‑B +0.79% | E113: =A116 -> NIBE B +0.75% | F113: =A117 -> Addtech AB B +3.87% | G113: =A118 -> Trelleborg AB B +0.47% | H113: =A119 -> AAK AB +0.47%
A114: Perf (prev recs): | B114: =ISNUMBER(LEFT(A114,4)+1-1) -> FALSE | C114: =IF(B114,LEFT(A114,10),C113) -> 2025-10-24 | D114: =A116 -> NIBE B +0.75% | E114: =A117 -> Addtech AB B +3.87% | F114: =A118 -> Trelleborg AB B +0.47% | G114: =A119 -> AAK AB +0.47% | H114: =A120 -> Avg +1.27%
A115: SKF‑B +0.79% | B115: =ISNUMBER(LEFT(A115,4)+1-1) -> FALSE | C115: =IF(B115,LEFT(A115,10),C114) -> 2025-10-24 | D115: =A117 -> Addtech AB B +3.87% | E115: =A118 -> Trelleborg AB B +0.47% | F115: =A119 -> AAK AB +0.47% | G115: =A120 -> Avg +1.27% | H115: =A121 -> S&P500 +0.00%
A116: NIBE B +0.75% | B116: =ISNUMBER(LEFT(A116,4)+1-1) -> FALSE | C116: =IF(B116,LEFT(A116,10),C115) -> 2025-10-24 | D116: =A118 -> Trelleborg AB B +0.47% | E116: =A119 -> AAK AB +0.47% | F116: =A120 -> Avg +1.27% | G116: =A121 -> S&P500 +0.00% | H116: =A122 -> 0
A117: Addtech AB B +3.87% | B117: =ISNUMBER(LEFT(A117,4)+1-1) -> FALSE | C117: =IF(B117,LEFT(A117,10),C116) -> 2025-10-24 | D117: =A119 -> AAK AB +0.47% | E117: =A120 -> Avg +1.27% | F117: =A121 -> S&P500 +0.00% | G117: =A122 -> 0 | H117: =A123 -> 2025-10-25 - Saturday
A118: Trelleborg AB B +0.47% | B118: =ISNUMBER(LEFT(A118,4)+1-1) -> FALSE | C118: =IF(B118,LEFT(A118,10),C117) -> 2025-10-24 | D118: =A120 -> Avg +1.27% | E118: =A121 -> S&P500 +0.00% | F118: =A122 -> 0 | G118: =A123 -> 2025-10-25 - Saturday | H118: =A124 -> Recs:
... A121: S&P500 +0.00% | B121: =ISNUMBER(LEFT(A121,4)+1-1) -> FALSE | C121: =IF(B121,LEFT(A121,10),C120) -> 2025-10-24 | D121: =A123 -> 2025-10-25 - Saturday | E121: =A124 -> Recs: | F121: =A125 -> AMD – Advanced Micro Devices Inc. | G121: =A126 -> MSFT – Microsoft Corp. | H121: =A127 -> SAND – Sandstorm Gold Ltd.
B122: =ISNUMBER(LEFT(A122,4)+1-1) -> FALSE | C122: =IF(B122,LEFT(A122,10),C121) -> 2025-10-24 | D122: =A124 -> Recs: | E122: =A125 -> AMD – Advanced Micro Devices Inc. | F122: =A126 -> MSFT – Microsoft Corp. | G122: =A127 -> SAND – Sandstorm Gold Ltd. | H122: =A128 -> ERIC – Ericsson AB
A123: 2025-10-25 - Saturday | B123: =ISNUMBER(LEFT(A123,4)+1-1) -> TRUE | C123: =IF(B123,LEFT(A123,10),C122) -> 2025-10-25 | D123: =A125 -> AMD – Advanced Micro Devices Inc. | E123: =A126 -> MSFT – Microsoft Corp. | F123: =A127 -> SAND – Sandstorm Gold Ltd. | G123: =A128 -> ERIC – Ericsson AB | H123: =A129 -> TELIA – Telia Company AB
A124: Recs: | B124: =ISNUMBER(LEFT(A124,4)+1-1) -> FALSE | C124: =IF(B124,LEFT(A124,10),C123) -> 2025-10-25 | D124: =A126 -> MSFT – Microsoft Corp. | E124: =A127 -> SAND – Sandstorm Gold Ltd. | F124: =A128 -> ERIC – Ericsson AB | G124: =A129 -> TELIA – Telia Company AB | H124: =A130 -> Perf (prev recs):
A125: AMD – Advanced Micro Devices Inc. | B125: =ISNUMBER(LEFT(A125,4)+1-1) -> FALSE | C125: =IF(B125,LEFT(A125,10),C124) -> 2025-10-25 | D125: =A127 -> SAND – Sandstorm Gold Ltd. | E125: =A128 -> ERIC – Ericsson AB | F125: =A129 -> TELIA – Telia Company AB | G125: =A130 -> Perf (prev recs): | H125: =A131 -> SKF‑B +0.42%
A126: MSFT – Microsoft Corp. | B126: =ISNUMBER(LEFT(A126,4)+1-1) -> FALSE | C126: =IF(B126,LEFT(A126,10),C125) -> 2025-10-25 | D126: =A128 -> ERIC – Ericsson AB | E126: =A129 -> TELIA – Telia Company AB | F126: =A130 -> Perf (prev recs): | G126: =A131 -> SKF‑B +0.42% | H126: =A132 -> EVO.ST -0.55%
A127: SAND – Sandstorm Gold Ltd. | B127: =ISNUMBER(LEFT(A127,4)+1-1) -> FALSE | C127: =IF(B127,LEFT(A127,10),C126) -> 2025-10-25 | D127: =A129 -> TELIA – Telia Company AB | E127: =A130 -> Perf (prev recs): | F127: =A131 -> SKF‑B +0.42% | G127: =A132 -> EVO.ST -0.55% | H127: =A133 -> MSFT +1.18%
...

Sheet Clean
A1: String | B1: Rec 1 | C1: Rec 2 | D1: Rec 3 | E1: Rec 4 | F1: Rec 5
A2: ='Sum and Cleaner'!$A$2 -> 2025-11-05 - Wednesday | B2: NVDA – NVIDIA Corporation | C2: AAPL – Apple Inc. | D2: MSFT – Microsoft Corporation | E2: ERICb.ST – Telefonaktiebolaget LM Ericsson B | F2: BOL – The Boliden Company
A3: ='Sum and Cleaner'!$A$18 -> 2025-11-06 - Thursday | B3: SECU-B.ST – Securitas AB | C3: ERIC-B.ST – Ericsson B | D3: TELIA.ST – Telia Company | E3: SAAB-B.ST – Saab AB | F3: VOLV-B.ST – AB Volvo B
A4: ='Sum and Cleaner'!$A$28 -> 2025-11-07 - Friday | B4: TELIA.ST – Telia Company | C4: ERIC-B.ST – Ericsson B | D4: SAAB-B.ST – Saab AB | E4: VOLV-B.ST – AB Volvo B | F4: NOK – Nokia Corporation
A5: ='Sum and Cleaner'!$A$44 -> 2025-11-08 - Saturday | B5: SWEC-B.ST – Sweco AB | C5: ATCO-A.ST – Atlas Copco A | D5: HEXA-B.ST – Hexagon AB | E5: INVE-B.ST – Investor AB | F5: SAND.ST – Sandvik AB
A6: ='Sum and Cleaner'!$A$60 -> 2025-11-09 - Sunday | B6: SWEC-B.ST – Sweco AB | C6: ERIC-B.ST – Ericsson AB B | D6: SSAB-B.ST – SSAB AB B | E6: SHBa.ST – Handelsbanken AB | F6: INVE-B.ST – Investor AB B
A7: ='Sum and Cleaner'!$A$76 -> 2025-11-10 - Monday | B7: HEXA‑B.ST – Hexagon AB | C7: AZN – AstraZeneca plc | D7: EQTAB.ST – EQT AB | E7: SAABb.ST – Saab AB B | F7: BOL.ST – Boliden AB B
A8: ='Sum and Cleaner'!$A$91 -> 2025-10-23 - Thursday | B8: TSLA – Tesla Inc | C8: IBM – International Business Machines Corp | D8: NKE – Nike Inc | E8: SAND – Sandstorm Gold Ltd | F8: SEB_A – SEB AB
A9: ='Sum and Cleaner'!$A$107 -> 2025-10-24 - Friday | B9: TELIA – Telia Company AB | C9: PCELL – PowerCell Sweden AB | D9: SEB_A – SEB AB | E9: ERIC – Ericsson AB | F9: VOLV B – Volvo AB
A10: ='Sum and Cleaner'!$A$123 -> 2025-10-25 - Saturday | B10: AMD – Advanced Micro Devices Inc. | C10: MSFT – Microsoft Corp. | D10: SAND – Sandstorm Gold Ltd. | E10: ERIC – Ericsson AB | F10: TELIA – Telia Company AB
A11: ='Sum and Cleaner'!$A$139 -> 2025-10-26 - Sunday | B11: AAPL – Apple Inc. | C11: MSFT – Microsoft Corp. | D11: ERIC – Ericsson AB | E11: ADS – Adidas AG | F11: SAP – SAP SE
A12: ='Sum and Cleaner'!$A$155 -> 2025-10-27 - Monday | B12: AAPL – Apple Inc. | C12: MSFT – Microsoft Corp. | D12: TELIA – Telia Company AB | E12: NVIDIA – NVIDIA Corp. | F12: EXXON – Exxon Mobil Corp.
A13: ='Sum and Cleaner'!$A$171 -> 2025-10-28 - Tuesday | B13: AAPL – Apple Inc. | C13: MSFT – Microsoft Corp. | D13: GOOGL – Alphabet Inc. | E13: TSLA – Tesla Inc. | F13: TELIA – Telia Company AB
A14: ='Sum and Cleaner'!$A$181 -> 2025-11-11 - Tuesday | B14: AZN – AstraZeneca plc | C14: EQTAB.ST – EQT AB | D14: HEXA‑B.ST – Hexagon AB | E14: SAABb.ST – Saab AB B | F14: BOL.ST – Boliden AB
A15: ='Sum and Cleaner'!$A$197 -> 2025-11-12 - Wednesday | B15: AZN – AstraZeneca plc | C15: EQT.ST – EQT AB | D15: HEXA‑B.ST – Hexagon AB | E15: SAABb.ST – Saab AB B | F15: BOL.ST – Boliden AB
A16: ='Sum and Cleaner'!$A$213 -> 2025-11-13 - Thursday | B16: MSFT – Microsoft Corporation | C16: NVDA – NVIDIA Corporation | D16: SAAB B – Saab AB B | E16: BOL – Boliden AB | F16: SKF – SKF AB
A17: ='Sum and Cleaner'!$A$229 -> 2025-11-14 - Friday | B17: ERIC – Telefonaktiebolaget LM Ericsson | C17: MSFT – Microsoft Corporation | D17: NVDA – NVIDIA Corporation | E17: VOLV‑B.ST – AB Volvo B | F17: BOL.ST – Boliden AB
A18: ='Sum and Cleaner'!$A$245 -> 2025-11-15 - Saturday | B18: MSFT – Microsoft Corporation | C18: NVDA – NVIDIA Corporation | D18: APM – APM Terminals | E18: LACX – LACX Mining Corp | F18: KBH – KB Home
A19: ='Sum and Cleaner'!$A$261 -> 2025-11-16 - Sunday | B19: STOR B.ST – Storskogen Group AB Simply Wall St | C19: BOL.ST – Boliden AB Investing.com+1 | D19: MSFT – Microsoft Corporation | E19: NVDA – NVIDIA Corporation | F19: SSAB B.ST – SSAB AB Wikipedia
A20: ='Sum and Cleaner'!$A$277 -> 2025-11-17 - Monday | B20: AAPL – Apple Inc. | C20: CSCO – Cisco Systems Inc. | D20: CAT – Caterpillar Inc. | E20: BHP – BHP Group Ltd. | F20: SKLGF – SKF Group (Class B, Sweden)
A21: ='Sum and Cleaner'!$A$293 -> 2025-11-18 - Tuesday | B21: AAPL – Apple Inc. | C21: CSCO – Cisco Systems Inc. | D21: CAT – Caterpillar Inc.
A22: ='Sum and Cleaner'!$A$298 -> 2025-10-14 - Tuesday | B22: ERIC – Telefonaktiebolaget LM Ericsson | C22: SAAB-B.ST – Saab AB | D22: AZN.ST – AstraZeneca PLC | E22: AMD – Advanced Micro Devices, Inc. | F22: MP – MP Materials Corp.
A23: ='Sum and Cleaner'!$A$313 -> 2025-10-16 - Thursday | B23: VOLV-B.ST – Volvo | C23: NIBE-B.ST – Nibe Industrier | D23: SPOT – Spotify Technology | E23: TSLA – Tesla | F23: SHEL – Shell
A24: ='Sum and Cleaner'!$A$328 -> 2025-10-18 - Saturday | B24: ERIC – Ericsson | C24: SAND.ST – Sandvik | D24: AAPL – Apple | E24: RIO – Rio Tinto | F24: ORCL – Oracle
A25: ='Sum and Cleaner'!$A$343 -> 2025-10-19 - Sunday | B25: SKF-B.ST – SKF | C25: EVO.ST – Evolution AB | D25: MSFT – Microsoft | E25: NVO – Novo Nordisk | F25: BP – BP Plc
A26: ='Sum and Cleaner'!$A$358 -> 2025-10-21 - Tuesday | B26: AAPL – Apple | C26: TSLA – Tesla | D26: SHEL – Shell | E26: RIO – Rio Tinto | F26: ERIC – Ericsson
A27: ='Sum and Cleaner'!$A$373 -> 2025-10-22 - Wednesday | B27: SHB A – Handelsbanken | C27: SAABB – Saab AB | D27: SSAB A – SSAB AB | E27: AAPL – Apple Inc | F27: SHEL – Shell plc
A28: ='Sum and Cleaner'!$A$394 -> 2025‑10‑29 - Wednesday | B28: AAPL – Apple Inc. | C28: MSFT – Microsoft Corp. | D28: ASML – ASML Holding NV | E28: VOLV B – Volvo AB B‑share | F28: BABA – Alibaba Group Holding Ltd
A29: ='Sum and Cleaner'!$A$410 -> 2025-10-30 - Thursday | B29: TER – Teradyne Inc. | C29: CAT – Caterpillar Inc. | D29: W – Wayfair Inc. | E29: AVGO – Broadcom Inc. | F29: AMD – Advanced Micro Devices Inc.
A30: ='Sum and Cleaner'!$A$426 -> 2025-10-31 - Friday | B30: MSFT – Microsoft Corp. | C30: GOOGL – Alphabet Inc. | D30: VOLV B – Volvo AB Class B | E30: ASML – ASML Holding NV | F30: BA – Boeing Co.
A31: ='Sum and Cleaner'!$A$442 -> 2025-11-01 - Saturday | B31: AMZN – Amazon.com Inc | C31: AAPL – Apple Inc | D31: EQTAB.ST – EQT AB Class B | E31: CAT – Caterpillar Inc | F31: GOOGL – Alphabet Inc
A32: ='Sum and Cleaner'!$A$458 -> 2025-11-02 - Sunday | B32: EQTAB.ST – EQT AB Class B (Sweden) | C32: MSFT – Microsoft Corporation | D32: NVDA – NVIDIA Corporation | E32: JNJ – Johnson & Johnson | F32: XOM – Exxon Mobil Corporation
A33: ='Sum and Cleaner'!$A$474 -> 2025-11-03 - Monday | B33: SAAB B.ST – Saab AB | C33: SAVE.ST – Nordnet AB | D33: EQTAB.ST – EQT AB Class B | E33: ERIC B.ST – Ericsson AB | F33: AAPL – Apple Inc
A34: ='Sum and Cleaner'!$A$490 -> 2025-11-04 - Tuesday | B34: EQTAB.ST – EQT AB Class B | C34: NVDA – NVIDIA Corporation | D34: VRTX – Vertex Pharmaceuticals | E34: DELL – Dell Technologies Inc. | F34: TELIA.ST – Telia Company
A35: ='Sum and Cleaner'!$A$516 -> 2025-11-19 - Wednesday | B35: CSCO – Cisco Systems Inc. | C35: AAPL – Apple Inc. | D35: CAT – Caterpillar Inc. | E35: BHP – BHP Group Ltd. | F35: SKFB.ST – SKF AB (Sweden)
A36: ='Sum and Cleaner'!$A$531 -> 2025-11-19 - Wednesday | B36: NVDA – NVIDIA Corp | C36: ERIC – Telefonaktiebolaget LM Ericsson | D36: VOLV-B.ST – AB Volvo (publ) B | E36: AZN.ST – AstraZeneca PLC | F36: VOLCAR-B.ST – Volvo Car AB (publ.)
A37: ='Sum and Cleaner'!$A$547 -> 2025-11-20 - Thursday | B37: NVDA – NVIDIA Corp | C37: AMD – Advanced Micro Devices Inc. | D37: WMT – Walmart Inc. | E37: SYNSAM.ST – Synsam AB (publ) | F37: HUFV-A.ST – Hufvudstaden AB (publ)
A38: ='Sum and Cleaner'!$A$563 -> 2025-11-21 - Friday | B38: NVDA – NVIDIA Corporation | C38: ERIC – Telefonaktiebolaget LM Ericsson | D38: WMT – Walmart Inc. | E38: TEL – Telia Company AB | F38: TAK – Takkt AG
A39: ='Sum and Cleaner'!$A$579 -> 2025-11-22 - Saturday | B39: AAPL – Apple Inc. | C39: SAP – SAP SE | D39: SAND.ST – Sandvik AB | E39: ORSTED.CO – Ørsted A/S | F39: TSLA – Tesla Inc.
A40: ='Sum and Cleaner'!$A$595 -> 2025-11-23 - Sunday | B40: SAAB B – Saab AB | C40: WBD – Warner Bros. Discovery, Inc. | D40: COST – Costco Wholesale Corporation | E40: LRCX – Lam Research Corporation | F40: ASML – ASML Holding N.V.
A41: ='Sum and Cleaner'!$A$611 -> 2025-11-24 - Monday | B41: WBD – Warner Bros. Discovery, Inc. (media) | C41: COST – Costco Wholesale Corporation (consumer retail) | D41: LRCX – Lam Research Corporation (semiconductor equipment) | E41: ASML – ASML Holding N.V. (chip lithography) | F41: ALLIGO B – Alligo AB (publ) (Sweden trade distribution)
A42: ='Sum and Cleaner'!$A$627 -> 2025-11-25 - Tuesday | B42: ASML – ASML Holding N.V. (semiconductor equipment) | C42: LRCX – Lam Research Corporation (semiconductor manufacturing) | D42: COST – Costco Wholesale Corporation (consumer retail) | E42: ALB – Albemarle Corporation (lithium/EV materials) | F42: PTC – PTC Inc. (industrial software)
A43: ='Sum and Cleaner'!$A$653 -> 2025‑12‑12 / 08:15 - Friday | B43: NVDA - Nvidia (momentum from AI demand and trading strength) | C43: MSFT - Microsoft (strong cloud earnings sentiment driving flow) | D43: TSLA - Tesla (price breakout and volume spike) | E43: BAC - Bank of America (financials strength on rates outlook) | F43: XOM - Exxon Mobil (energy sector rebound)
A44: ='Sum and Cleaner'!$A$664 -> 2025‑12‑13 / 08:15 - Saturday | B44: COIN - Coinbase Global Inc (crypto‑equity trading interest rising)TS2 Tech | C44: CVX - Chevron Corp (analyst forecasts and capex catalyst)TS2 Tech | D44: CRON - Cronos Group Inc (cannabis sector buzz on rescheduling)TS2 Tech | E44: INTU - Intuit Inc (AI and targets ahead of earnings)TS2 Tech | F44: ALNT - Allient Corp (bullish industrial tech signal)Investors
A45: ='Sum and Cleaner'!$A$675 -> 2025‑12‑14 / 08:15 - Sunday | B45: TSLA - Tesla Inc (momentum from positive technical and product catalysts)Investors.com | C45: GE - GE Aerospace (industrial strength and near buy point on recent flow)Investors.com | D45: LLY - Eli Lilly & Co (healthcare resilience and data‑driven upside)Investors.com | E45: JPM - JPMorgan Chase & Co (financials strength amid rotation)Investors.com | F45: WBD - Warner Bros Discovery (takeover bid driving elevated activity)The Guardian
A46: ='Sum and Cleaner'!$A$686 -> 2025-12-15 / 08:15 - Monday | B46: BAC – Bank of America Corp (record highs and Fed rate cut narrative driving financial flows) TechStock² | C46: WBD – Warner Bros Discovery (takeover battle boosting share activity) The Guardian+1 | D46: IBM – International Business Machines (acquisition news lifting tech sentiment) Barron's | E46: COIN – Coinbase Global Inc (crypto-linked equities moving with Bitcoin strength) Barron's | F46: CRH – CRH plc (S&P 500 inclusion announcement lifting name) Barron's

Sheet List to fetch
A1: Rec 1 | B1: Ticker
A2: NVDA – NVIDIA Corporation | B2: =LEFT(A2,6) -> NVDA –
A3: SECU-B.ST – Securitas AB | B3: =LEFT(A3,6) -> SECU-B
A4: TELIA.ST – Telia Company | B4: =LEFT(A4,6) -> TELIA.
A5: SWEC-B.ST – Sweco AB | B5: =LEFT(A5,6) -> SWEC-B
A6: SWEC-B.ST – Sweco AB | B6: =LEFT(A6,6) -> SWEC-B
A7: HEXA‑B.ST – Hexagon AB | B7: =LEFT(A7,6) -> HEXA‑B
A8: TSLA – Tesla Inc | B8: =LEFT(A8,6) -> TSLA –
A9: TELIA – Telia Company AB | B9: =LEFT(A9,6) -> TELIA
A10: AMD – Advanced Micro Devices Inc. | B10: =LEFT(A10,6) -> AMD –
A11: AAPL – Apple Inc. | B11: =LEFT(A11,6) -> AAPL –
A12: AAPL – Apple Inc. | B12: =LEFT(A12,6) -> AAPL –
A13: AAPL – Apple Inc. | B13: =LEFT(A13,6) -> AAPL –
... A230: CRH – CRH plc (S&P 500 inclusion announcement lifting name) Barron's | B230: =LEFT(A230,6) -> CRH –

Sheet changed on 161225
A1: For a short term trade, to be opened in the morning and closed at end of day, search for the latest major global news. Recommend EXACTLY 5 BUY tickers for short-term trade based on whatever you think is relevant. add very short reasoning after the recommendation.
A3: Start with one line containing the local date and day of week in Stockholm time formatted exactly as:
A4: YYYY-MM-DD / HH:MM - Monday
A6: Recs:
A7: TICKER – Company (short reasoning)
A8: TICKER – Company (short reasoning)
A9: TICKER – Company (short reasoning)
A10: TICKER – Company (short reasoning)
A11: TICKER – Company (short reasoning)
A14: Used to be: FRESH CATALYSTS AND MOMENTUM

Sheet 2026-01-04 to 2026-05-19 longeq
A1: ChatGPT | B1: longeq
B2: longeq
B3: longeq
A4: Updated memory | B4: longeq
B5: longeq
A6: They are 0 because no price data was retrieved for those Indian tickers. | B6: longeq
A7: This happens for one of three mechanical reasons: | B7: longeq
B8: longeq
A9: 1. They do not trade on US or EU exchanges and the fetch layer used here does not return NSE/BSE closes. | B9: longeq
A10: 2. On non-trading days (weekend or holiday), the system falls back to “no change” when no prior close is available. | B10: longeq
A11: 3. Without two independent price sources for those symbols, the return calculator fails and defaults to 0 rather than fabricate numbers. | B11: longeq
B12: longeq
A13: This is a data-availability issue, not a market-movement result. | B13: longeq
B14: longeq
A15: 2025-12-10 / 08:16 - Wednesday | B15: longeq
B16: longeq
A17: Recs: | B17: longeq
A18: NVDA – Nvidia | B18: longeq
A19: ORCL – Oracle | B19: longeq
A20: SHEL – Shell | B20: longeq
A21: BHP – BHP Group | B21: longeq
A22: RIO – Rio Tinto | B22: longeq
B23: longeq
A24: Prev days return S&P500 +0.00% | B24: longeq
B25: longeq
A26: 2025‑12‑11 / 08:15 - Thursday | B26: longeq
B27: longeq
A28: Recs: | B28: longeq
A29: GEV - GE Vernova Inc (breakout after strong catalyst and technical momentum) | B29: longeq
A30: PLTR - Palantir Technologies (recent contract win and positive flow) | B30: longeq
A31: SATS - EchoStar Corp (premarket strength and sector interest) | B31: longeq
A32: AVTR - Avantor Inc (premarket gains signaling momentum) | B32: longeq
A33: FSLR - First Solar (sector news on project supply momentum) | B33: longeq
B34: longeq
A35: Prev days return S&P500 +0.67% | B35: longeq
B36: longeq
A37: 2025‑12‑12 / 08:15 - Friday | B37: longeq
B38: longeq
A39: Recs: | B39: longeq
A40: NVDA - Nvidia (momentum from AI demand and trading strength) | B40: longeq
A41: MSFT - Microsoft (strong cloud earnings sentiment driving flow) | B41: longeq
A42: TSLA - Tesla (price breakout and volume spike) | B42: longeq
A43: BAC - Bank of America (financials strength on rates outlook) | B43: longeq
A44: XOM - Exxon Mobil (energy sector rebound) | B44: longeq
B45: longeq
A46: Prev days return S&P500 +0.30% | B46: longeq
B47: longeq
A48: 2025‑12‑13 / 08:15 - Saturday | B48: longeq
B49: longeq
A50: Recs: | B50: longeq
A51: COIN - Coinbase Global Inc (crypto‑equity trading interest rising) | B51: longeq
A52: CVX - Chevron Corp (analyst forecasts and capex catalyst) | B52: longeq
A53: CRON - Cronos Group Inc (cannabis sector buzz on rescheduling) | B53: longeq
A54: INTU - Intuit Inc (AI and targets ahead of earnings) | B54: longeq
A55: ALNT - Allient Corp (bullish industrial tech signal) | B55: longeq
B56: longeq
A57: Prev days return S&P500 ‑1.07% | B57: longeq
B58: longeq
A59: 2025‑12‑14 / 08:15 - Sunday | B59: longeq
B60: longeq
A61: Recs: | B61: longeq
A62: TSLA - Tesla Inc (momentum from positive technical and product catalysts) | B62: longeq
A63: GE - GE Aerospace (industrial strength and near buy point on recent flow) | B63: longeq
A64: LLY - Eli Lilly & Co (healthcare resilience and data‑driven upside) | B64: longeq
A65: JPM - JPMorgan Chase & Co (financials strength amid rotation) | B65: longeq
A66: WBD - Warner Bros Discovery (takeover bid driving elevated activity) | B66: longeq
B67: longeq
A68: Prev days return S&P500 ‑1.07% | B68: longeq
B69: longeq
A70: 2025-12-15 / 08:15 - Monday | B70: longeq
B71: longeq
A72: Recs: | B72: longeq
A73: BAC – Bank of America Corp (record highs and Fed rate cut narrative driving financial flows) | B73: longeq
A74: WBD – Warner Bros Discovery (takeover battle boosting share activity) | B74: longeq
A75: IBM – International Business Machines (acquisition news lifting tech sentiment) | B75: longeq
A76: COIN – Coinbase Global Inc (crypto-linked equities moving with Bitcoin strength) | B76: longeq
A77: CRH – CRH plc (S&P 500 inclusion announcement lifting name) | B77: longeq
B78: longeq
A79: Prev days return S&P500 -1.07% | B79: longeq
B80: longeq
A81: 2025-12-16 / 08:15 - Tuesday | B81: longeq
B82: longeq
A83: Recs: | B83: longeq
A84: SNDK - Sandisk (after‑hours move suggests upside into open) | B84: longeq
A85: HD - Home Depot (retail strength catalysts ahead of open) | B85: longeq
A86: CVNA - Carvana (continued momentum and analyst interest) | B86: longeq
A87: LRCX - Lam Research (raised target and momentum into morning) | B87: longeq
A88: DIS - Walt Disney (insider buy and narrative update) | B88: longeq
B89: longeq
A90: Prev day S&P500 return -0.16% (index slipped as markets awaited data) | B90: longeq
B91: longeq
A92: 2025-12-17 / 08:20 - Wednesday | B92: longeq
B93: longeq
A94: Recs: | B94: longeq
A95: TSLA – Tesla Inc (closed at record high yesterday, momentum signal) | B95: longeq
A96: BAC – Bank of America Corp (analyst catalysts and financial flows) | B96: longeq
A97: KO – Coca-Cola Co (analyst target upgrades and defensive demand) | B97: longeq
A98: XOM – Exxon Mobil Corp (oil price strength from geopolitical tension) | B98: longeq
A99: META – Meta Platforms Inc (AI strategy outlook supportive) | B99: longeq
B100: longeq
...

Sheet 2025-12-05 to 2026-05-19 longal
A1: ChatGPT | B1: LONGALL
B2: LONGALL
B3: LONGALL
A4: For a short term trade, to be opened in the morning and closed at end of day, search for the latest major global news. Recommend EXACTLY 5 LONG instruments for short-term trade based on whatever you think is relevant. The investment universe may include equities, equity indices, commodities, FX, rates, and their liquid derivatives (futures, options, or major ETFs). Add very short reasoning after each recommendation. Start with one line containing the local date and day of week in Stockholm time formatted exactly as: YYYY-MM-DD / HH:MM - Monday Recs: SYMBOL – Instrument name (short reasoning) SYMBOL – Instrument name (short reasoning) SYMBOL – Instrument name (short reasoning) SYMBOL – Instrument name (short reasoning) SYMBOL – Instrument name (short reasoning) | B4: LONGALL
B5: LONGALL
A6: 2026-01-05 / 07:00 - Monday | B6: LONGALL
B7: LONGALL
A8: Recs: | B8: LONGALL
A9: SPY – major US equity ETF likely to benefit from early-year recovery sentiment after Santa Claus rally and dip bounce | B9: LONGALL
A10: BTCUSD – Bitcoin showing breakout momentum above recent highs suggesting continuation into new week | B10: LONGALL
A11: FTSE – UK index breaking key level reflecting strong European risk appetite and rate cut expectations | B11: LONGALL
A12: CL1 – WTI crude futures likely supported by geopolitical risk and supply dynamics referenced in global markets news | B12: LONGALL
A13: DAX – German equity index poised to extend gains on eurozone growth and dovish central bank expectations | B13: LONGALL
B14: LONGALL
A15: set this up as a daily task at 8:15 | B15: LONGALL
A16: Updated memory | B16: LONGALL
A17: Generate daily long trade ideas | B17: LONGALL
A18: Daily at 3:30 AM | B18: LONGALL
A19: Daily task scheduled. Runs every day at 08:15 Stockholm time. | B19: LONGALL
B20: LONGALL
A21: 2026‑01‑05 / 08:16 - Monday | B21: LONGALL
B22: LONGALL
A23: Recs: | B23: LONGALL
A24: NIKKEI – Japan Nikkei 225 Index (Asia stocks rally on resilience despite geopolitical stress) | B24: LONGALL
A25: HSI – Hang Seng Index (Chinese market strength above key level on optimism) | B25: LONGALL
A26: XAUUSD – Gold Spot (safe haven demand rising amid geopolitical risk) | B26: LONGALL
A27: AUDUSD – AUD/USD FX (AUD holding near uptrend support as US dollar capped) | B27: LONGALL
A28: BTCUSD – Bitcoin (crypto showing strength with broader risk asset gains) | B28: LONGALL
B29: LONGALL
A30: 2026‑01‑06 / 08:15 - Tuesday | B30: LONGALL
B31: LONGALL
A32: Recs: | B32: LONGALL
A33: DJI - Dow Jones Industrial Average futures (global equities rally led by energy and banks) | B33: LONGALL
A34: FTSE - FTSE 100 Index (defence and mining strength on geopolitical risk) | B34: LONGALL
A35: CL1 - WTI Crude Oil futures (energy stocks strong post‑Venezuela news) | B35: LONGALL
A36: XAU - Gold Spot (safe‑haven asset rising on uncertainty) | B36: LONGALL
A37: USDJPY - USD/JPY FX (dollar weakness narrative may fuel carry and risk flows) | B37: LONGALL
B38: LONGALL
A39: 2026-01-07 / 08:15 - Monday | B39: LONGALL
B40: LONGALL
A41: Recs: | B41: LONGALL
A42: SPY - SPDR S&P 500 ETF (global equities up on strong inflows and optimism) | B42: LONGALL
A43: FTSE - FTSE 100 Index (miners and energy driving higher highs) | B43: LONGALL
A44: XAUUSD - Gold Spot (safe-haven rising after geopolitical shocks) | B44: LONGALL
A45: WTI - WTI Crude Oil futures (oil supported despite geopolitical risk) | B45: LONGALL
A46: EURUSD - EUR/USD FX (dollar steadies with euro supported ahead of data) | B46: LONGALL
B47: LONGALL
A48: 2026‑01‑08 / 08:15 - Thursday | B48: LONGALL
B49: LONGALL
A50: SPY – S&P 500 ETF (global stocks rally broadly including financials and materials) | B50: LONGALL
A51: DAX – Germany 40 Index (European equities hitting record highs) | B51: LONGALL
A52: WTI – Crude Oil futures (oil pricing influenced by geopolitical developments) | B52: LONGALL
A53: AUDUSD – AUD/USD FX (AUD supported by macro tailwinds and policy outlook) | B53: LONGALL
A54: GLD – Gold Spot (precious metals buoyed by risk and inflation considerations) | B54: LONGALL
B55: LONGALL
A56: 2026-01-09 / 08:16 - Friday | B56: LONGALL
B57: LONGALL
A58: SPY - S&P 500 ETF (global equity funds saw strong inflows and risk appetite; broad markets up) | B58: LONGALL
A59: XLE - Energy Select Sector ETF (US energy stocks rallied on Venezuelan geopolitical shift) | B59: LONGALL
A60: WTI/CL1 - WTI Crude Oil futures (oil rebounded in recent trading on macro and supply news) | B60: LONGALL
A61: GLD - Gold Spot (precious metals supported by safe-haven demand and inflows) | B61: LONGALL
A62: USD/JPY - FX (yen weaker and risk assets supported by softer dollar backdrop) | B62: LONGALL
B63: LONGALL
A64: 2026-01-10 / 08:14 - Saturday | B64: LONGALL
B65: LONGALL
A66: SPY - S&P 500 ETF (U.S. equities at records on broad rally; risk assets supported) | B66: LONGALL
A67: DAX - Germany 40 Index (European stocks at highs led by miners and tech) | B67: LONGALL
A68: WTI - Crude Oil futures (oil prices rising on supply/geopolitical risk) | B68: LONGALL
A69: GLD - Gold Spot (precious metals bid amid market uncertainty) | B69: LONGALL
A70: EURUSD - EUR/USD FX (euro holding firm as dollar pressure persists) | B70: LONGALL
B71: LONGALL
A72: 2026-01-11 / 08:15 - Sunday | B72: LONGALL
B73: LONGALL
A74: SPY - S&P 500 futures (global equities at record levels; strong broad momentum) | B74: LONGALL
A75: XLF - Financials ETF (bank earnings and bond market activity supporting financials) | B75: LONGALL
A76: XME - Metals & Mining ETF (miner consolidation news and commodity strength) | B76: LONGALL
A77: XAUUSD - Gold (safe haven strength with price testing upside levels) | B77: LONGALL
A78: EURUSD - FX (euro stronger on macro flows versus dollar) | B78: LONGALL
B79: LONGALL
A80: 2026‑01‑12 / 08:16 - Monday | B80: LONGALL
B81: LONGALL
A82: XAUUSD – Gold (safe‑haven surge to record highs on geopolitical risk and Fed uncertainty) | B82: LONGALL
A83: COPPER – Copper futures (industrial metals hitting multi‑year highs on supply tightness and demand) | B83: LONGALL
A84: US500 – S&P 500 futures (momentum intact from record highs despite early weakness) | B84: LONGALL
A85: USDCHF – USD/CHF FX (dollar weakness against safe‑haven CHF supports long CHF crosses lower vol) | B85: LONGALL
A86: CL1 – WTI crude oil futures (oil prices rising on Middle East tensions and supply concerns) | B86: LONGALL
B87: LONGALL
A88: 2026‑01‑13 / 08:15 - Tuesday | B88: LONGALL
B89: LONGALL
A90: GC=F – Gold futures (record highs on safe‑haven demand and Fed political risk) | B90: LONGALL
A91: CL=F – Crude Oil futures (prices up on Iran supply concerns and geopolitical risk) | B91: LONGALL
A92: N225 – Nikkei 225 index (Asian equities rally led by Japan at record levels) | B92: LONGALL
A93: USD/JPY – FX pair (yen weakness driving dollar strength trend) | B93: LONGALL
A94: SPY – S&P 500 ETF (US indexes near records with broad participation) | B94: LONGALL
B95: LONGALL
A96: 2026‑01‑14 / 08:15 - Monday | B96: LONGALL
B97: LONGALL
A98: ES1! - S&P 500 futures (indices bounce on Asian gains amid global optimism) | B98: LONGALL
A99: N225 - Nikkei 225 index (Japan stocks up sharply supporting global risk sentiment) | B99: LONGALL
A100: GC1! - Gold futures (safe‑haven demand driving prices higher) | B100: LONGALL
...

Sheet 2026-01-04 to 2026-05-19 short
A1: ChatGPT | B1: SHORT
B2: SHORT
B3: SHORT
A4: For a short term trade, to be opened in the morning and closed at end of day, search for the latest major global news. Recommend EXACTLY 5 SHORT instruments for short-term trade based on whatever you think is relevant. The investment universe may include equities, equity indices, commodities, FX, rates, and their liquid derivatives (futures, options, or major ETFs). Add very short reasoning after each recommendation. Start with one line containing the local date and day of week in Stockholm time formatted exactly as: YYYY-MM-DD / HH:MM - Monday Recs: SYMBOL – Instrument name (short reasoning) SYMBOL – Instrument name (short reasoning) SYMBOL – Instrument name (short reasoning) SYMBOL – Instrument name (short reasoning) SYMBOL – Instrument name (short reasoning) | B4: SHORT
B5: SHORT
A6: 2026-01-04 / 08:00 - Sunday | B6: SHORT
B7: SHORT
A8: Recs: | B8: SHORT
A9: ES00 (E-mini S&P 500 futures) – risk-off pressure from geopolitical shocks (Venezuela capture) and mixed global equities suggests downside bias. | B9: SHORT
A10: WTI (Crude Oil futures) – short-term supply disruption risk priced in but directional uncertainty and potential pullback after recent surge. | B10: SHORT
A11: DXY (US Dollar Index) – prospect of Fed rate cuts and dollar weakness into 2026 could cause short-term corrective leg lower. | B11: SHORT
A12: XLF (Financial Select Sector SPDR ETF) – activist investor pressure and bank sector stress elevate short downside risk. | B12: SHORT
A13: NQ00 (E-mini Nasdaq 100 futures) – tech softness from profit-taking after 2025 gains implies potential intraday pullback. | B13: SHORT
B14: SHORT
A15: set this up as a daily task at 8:15 | B15: SHORT
A16: Generate short trade shorts | B16: SHORT
A17: Daily at 3:30 PM | B17: SHORT
A18: Task scheduled. Daily at 08:15 Stockholm time. | B18: SHORT
B19: SHORT
A20: 2026‑01‑05 / 08:15 - Monday | B20: SHORT
B21: SHORT
A22: SPY - broad US equity risk off, profit‑taking heavy after long run, valuation stretched. | B22: SHORT
A23: CL_F - crude oil futures weakening on supply expectations and technical pressure. | B23: SHORT
A24: XAGUSD - silver peaked then pulled back, technicals point to correction. | B24: SHORT
A25: USDJPY - FX showing US dollar capped and mixed risk appetite - short yen weakness. | B25: SHORT
A26: VIX - volatility index extremely low with asymmetric upside risk, anticipate repricing. | B26: SHORT
B27: SHORT
A28: isn't vix then should be Long if low | B28: SHORT
B29: SHORT
A30: Correct. | B30: SHORT
B31: SHORT
A32: If VIX is low, the directional trade is LONG VIX, not short. | B32: SHORT
A33: Low implied volatility implies asymmetric upside risk and mean reversion favors expansion. | B33: SHORT
A34: Shorting VIX only makes sense after a volatility spike, not at compressed levels. | B34: SHORT
B35: SHORT
A36: Conclusion: VIX was misclassified. A low-VIX regime invalidates it as a short candidate. | B36: SHORT
B37: SHORT
A38: please reiterate if there is any wrong "shorts" in last recommendation | B38: SHORT
A39: Updated memories | B39: SHORT
B40: SHORT
A41: Yes. Two errors. | B41: SHORT
B42: SHORT
A43: 1. VIX | B43: SHORT
A44: Wrong side. Low VIX implies LONG volatility, not short. Short VIX only after spikes. | B44: SHORT
B45: SHORT
A46: 2. USDJPY | B46: SHORT
A47: Reasoning inconsistent. “Short yen weakness” contradicts the trade. | B47: SHORT
A48: Short USDJPY equals long JPY strength. If expecting yen weakness, the position should be long USDJPY. | B48: SHORT
B49: SHORT
A50: All other shorts were directionally consistent. | B50: SHORT
B51: SHORT
A52: 2026‑01‑06 / 08:15 - Tuesday | B52: SHORT
B53: SHORT
A54: SENSEX (NSE) – Indian benchmark weakening with key stocks lagging, risk‑off setup. | B54: SHORT
A55: WTI (CL1) – crude oil down on oversupply and lower demand expectations. | B55: SHORT
A56: EUR/USD – pair below key resistance, short bias as downside persists. | B56: SHORT
A57: NKE – Nike weak relative to peers, risk of further downside (futures soft). | B57: SHORT
A58: SPY – broad US equity indices showing technical breakdown and bearish signals. | B58: SHORT
B59: SHORT
A60: 2026‑01‑07 / 08:15 - Wednesday | B60: SHORT
B61: SHORT
A62: SILVER (XAGUSD) - price downtrend confirmed below key levels with bearish momentum and break lower support. | B62: SHORT
A63: PLATINUM (XPTUSD) - sharp drops on recent session and technical weakness vs metals group. | B63: SHORT
A64: NIKKEI225 - Asian index shows mixed macro sentiment and Asian energy stocks lag, downside tilt. | B64: SHORT
A65: USOIL (CL1) - crude futures rolled over after geopolitical spike failed and trend loss. | B65: SHORT
A66: EURUSD - technical indicators in short frames signal bearish continuation after resistance rejection. | B66: SHORT
B67: SHORT
A68: 2026‑01‑08 / 08:16 - Thursday | B68: SHORT
B69: SHORT
A70: SPY – broad US equity futures showing weakness and technical pullback after rally exhaustion. | B70: SHORT
A71: CL=F – crude oil futures pressured by commodity index rebalancing with heavy sell orders expected. | B71: SHORT
A72: XAGUSD – silver facing significant selling pressure from annual commodity rebalancing. | B72: SHORT
A73: AUD/USD – currency pair hinting at pullback risk as USD regains footing and Aussie momentum falters. | B73: SHORT
A74: DAX – European index retreating from short‑term resistance with broad risk‑off price action. | B74: SHORT
B75: SHORT
A76: 2026-01-12 / 08:16 - Monday | B76: SHORT
B77: SHORT
A78: SPY – Index showing pre-market weakness from prior pullback and macro uncertainty. | B78: SHORT
A79: CL=F – Crude oil price momentum breaking lower with bearish technical signals. | B79: SHORT
A80: AAPL – Large cap tech under pressure and momentum weak vs peers. | B80: SHORT
A81: AUDUSD – FX bearish continuation bias as AUD outlook flagged weak by analysts. | B81: SHORT
A82: NQ=F – Nasdaq futures showing risk-off technical bias and sector rotation out of growth. | B82: SHORT
B83: SHORT
A84: 2026-01-12 / 08:15 - Monday | B84: SHORT
B85: SHORT
A86: N225 - Nikkei 225 futures (momentum fading near record highs with pullback risk) | B86: SHORT
A87: EURUSD - Euro vs US Dollar (weak tone, USD strength, EUR testing lower levels) | B87: SHORT
A88: BRN=F - Brent crude oil futures (price under pressure amid supply and geopolitical tensions) | B88: SHORT
A89: XAGUSD - Silver (bearish technical continuation pressure on support trendline) | B89: SHORT
A90: INDU - Dow Jones Industrial Average futures (broad market vulnerability despite recent highs) | B90: SHORT
B91: SHORT
A92: 2026‑01‑12 / 08:15 - Monday | B92: SHORT
B93: SHORT
A94: ABF.L – Associated British Foods (profit warning, shares down sharply on weak Primark & U.S. demand) | B94: SHORT
A95: SHEL.L – Shell PLC (energy stock sliding on weaker trading and narrowed guidance) | B95: SHORT
A96: GRG.L – Greggs PLC (flat profit outlook, subdued consumer confidence pressure) | B96: SHORT
A97: XAU=USD – Gold (price falling on commodity index adjustments and firm dollar) | B97: SHORT
A98: USD/SEK – US Dollar vs Swedish Krona (USD strength driving emerging market FX weakness) | B98: SHORT
B99: SHORT
A100: 2026‑01‑12 / 08:16 - Monday | B100: SHORT
...

Sheet Sheet6
A1: {=_xlfn.VSTACK(_xlfn._xlws.FILTER('2026-01-04 to 2026-05-19 longeq'!B:B,ISBLANK('2026-01-04 to 2026-05-19 longeq'!$A:$A)=FALSE,""),_xlfn._xlws.FILTER('2025-12-05 to 2026-05-19 longal'!B:B,ISBLANK('2025-12-05 to 2026-05-19 longal'!$A:$A)=FALSE,""),_xlfn._xlws.FILTER('2026-01-04 to 2026-05-19 short'!B:B,ISBLANK('2025-12-05 to 2026-05-19 longal'!$A:$A)=FALSE,""))} -> longeq | B1: {=_xlfn.VSTACK(_xlfn._xlws.FILTER('2026-01-04 to 2026-05-19 longeq'!A:A,ISBLANK('2026-01-04 to 2026-05-19 longeq'!$A:$A)=FALSE,""),_xlfn._xlws.FILTER('2025-12-05 to 2026-05-19 longal'!A:A,ISBLANK('2025-12-05 to 2026-05-19 longal'!$A:$A)=FALSE,""),_xlfn._xlws.FILTER('2026-01-04 to 2026-05-19 short'!A:A,ISBLANK('2025-12-05 to 2026-05-19 longal'!$A:$A)=FALSE,""))} -> ChatGPT | C1: Is date? | D1: Date
A2: longeq | B2: Updated memory | C2: =ISNUMBER(LEFT(B2,4)+1-1) -> FALSE | D2: =IF(C2,LEFT(B2,10),D1)+1-1 -> #VALUE!
A3: longeq | B3: They are 0 because no price data was retrieved for those Indian tickers. | C3: =ISNUMBER(LEFT(B3,4)+1-1) -> FALSE | D3: =IF(C3,LEFT(B3,10),D2)+1-1 -> #VALUE!
A4: longeq | B4: This happens for one of three mechanical reasons: | C4: =ISNUMBER(LEFT(B4,4)+1-1) -> FALSE | D4: =IF(C4,LEFT(B4,10),D3)+1-1 -> #VALUE!
A5: longeq | B5: 1. They do not trade on US or EU exchanges and the fetch layer used here does not return NSE/BSE closes. | C5: =ISNUMBER(LEFT(B5,4)+1-1) -> FALSE | D5: =IF(C5,LEFT(B5,10),D4)+1-1 -> #VALUE!
A6: longeq | B6: 2. On non-trading days (weekend or holiday), the system falls back to “no change” when no prior close is available. | C6: =ISNUMBER(LEFT(B6,4)+1-1) -> FALSE | D6: =IF(C6,LEFT(B6,10),D5)+1-1 -> #VALUE!
A7: longeq | B7: 3. Without two independent price sources for those symbols, the return calculator fails and defaults to 0 rather than fabricate numbers. | C7: =ISNUMBER(LEFT(B7,4)+1-1) -> FALSE | D7: =IF(C7,LEFT(B7,10),D6)+1-1 -> #VALUE!
A8: longeq | B8: This is a data-availability issue, not a market-movement result. | C8: =ISNUMBER(LEFT(B8,4)+1-1) -> FALSE | D8: =IF(C8,LEFT(B8,10),D7)+1-1 -> #VALUE!
A9: longeq | B9: 2025-12-10 / 08:16 - Wednesday | C9: =ISNUMBER(LEFT(B9,4)+1-1) -> TRUE | D9: =IF(C9,LEFT(B9,10),D8)+1-1 -> 46001
A10: longeq | B10: Recs: | C10: =ISNUMBER(LEFT(B10,4)+1-1) -> FALSE | D10: =IF(C10,LEFT(B10,10),D9)+1-1 -> 46001
A11: longeq | B11: NVDA – Nvidia | C11: =ISNUMBER(LEFT(B11,4)+1-1) -> FALSE | D11: =IF(C11,LEFT(B11,10),D10)+1-1 -> 46001
A12: longeq | B12: ORCL – Oracle | C12: =ISNUMBER(LEFT(B12,4)+1-1) -> FALSE | D12: =IF(C12,LEFT(B12,10),D11)+1-1 -> 46001
A13: longeq | B13: SHEL – Shell | C13: =ISNUMBER(LEFT(B13,4)+1-1) -> FALSE | D13: =IF(C13,LEFT(B13,10),D12)+1-1 -> 46001
... A40: longeq | B40: Prev days return S&P500 ‑1.07% | C40: =ISNUMBER(LEFT(B40,4)+1-1) -> FALSE | D40: =IF(C40,LEFT(B40,10),D39)+1-1 -> #VALUE!
A41: longeq | B41: 2025‑12‑14 / 08:15 - Sunday | C41: =ISNUMBER(LEFT(B41,4)+1-1) -> TRUE | D41: =IF(C41,LEFT(B41,10),D40) -> 2025‑12‑14 | E41: 2025‑12‑14
A42: longeq | B42: Recs: | C42: =ISNUMBER(LEFT(B42,4)+1-1) -> FALSE | D42: =IF(C42,LEFT(B42,10),D41)+1-1 -> #VALUE!
A43: longeq | B43: TSLA - Tesla Inc (momentum from positive technical and product catalysts) | C43: =ISNUMBER(LEFT(B43,4)+1-1) -> FALSE | D43: =IF(C43,LEFT(B43,10),D42)+1-1 -> #VALUE!
A44: longeq | B44: GE - GE Aerospace (industrial strength and near buy point on recent flow) | C44: =ISNUMBER(LEFT(B44,4)+1-1) -> FALSE | D44: =IF(C44,LEFT(B44,10),D43)+1-1 -> #VALUE!
A45: longeq | B45: LLY - Eli Lilly & Co (healthcare resilience and data‑driven upside) | C45: =ISNUMBER(LEFT(B45,4)+1-1) -> FALSE | D45: =IF(C45,LEFT(B45,10),D44)+1-1 -> #VALUE!
A46: longeq | B46: JPM - JPMorgan Chase & Co (financials strength amid rotation) | C46: =ISNUMBER(LEFT(B46,4)+1-1) -> FALSE | D46: =IF(C46,LEFT(B46,10),D45)+1-1 -> #VALUE!
A47: longeq | B47: WBD - Warner Bros Discovery (takeover bid driving elevated activity) | C47: =ISNUMBER(LEFT(B47,4)+1-1) -> FALSE | D47: =IF(C47,LEFT(B47,10),D46)+1-1 -> #VALUE!
A48: longeq | B48: Prev days return S&P500 ‑1.07% | C48: =ISNUMBER(LEFT(B48,4)+1-1) -> FALSE | D48: =IF(C48,LEFT(B48,10),D47)+1-1 -> #VALUE!
A49: longeq | B49: 2025-12-15 / 08:15 - Monday | C49: =ISNUMBER(LEFT(B49,4)+1-1) -> TRUE | D49: =IF(C49,LEFT(B49,10),D48)+1-1 -> 46006
A50: longeq | B50: Recs: | C50: =ISNUMBER(LEFT(B50,4)+1-1) -> FALSE | D50: =IF(C50,LEFT(B50,10),D49)+1-1 -> 46006
A51: longeq | B51: BAC – Bank of America Corp (record highs and Fed rate cut narrative driving financial flows) | C51: =ISNUMBER(LEFT(B51,4)+1-1) -> FALSE | D51: =IF(C51,LEFT(B51,10),D50)+1-1 -> 46006
A52: longeq | B52: WBD – Warner Bros Discovery (takeover battle boosting share activity) | C52: =ISNUMBER(LEFT(B52,4)+1-1) -> FALSE | D52: =IF(C52,LEFT(B52,10),D51)+1-1 -> 46006
A53: longeq | B53: IBM – International Business Machines (acquisition news lifting tech sentiment) | C53: =ISNUMBER(LEFT(B53,4)+1-1) -> FALSE | D53: =IF(C53,LEFT(B53,10),D52)+1-1 -> 46006
... A603: SHORT | B603: Task scheduled. Daily at 08:15 Stockholm time. | C603: =ISNUMBER(LEFT(B603,4)+1-1) -> FALSE | D603: =IF(C603,LEFT(B603,10),D602)+1-1 -> 46026
A604: SHORT | B604: 0 | C604: =ISNUMBER(LEFT(B604,4)+1-1) -> TRUE | D604: =IF(C604,LEFT(B604,10),D603)+1-1 -> 0
A605: SHORT | B605: 0 | C605: =ISNUMBER(LEFT(B605,4)+1-1) -> TRUE | D605: =IF(C605,LEFT(B605,10),D604)+1-1 -> 0
A606: SHORT | B606: CL_F - crude oil futures weakening on supply expectations and technical pressure. | C606: =ISNUMBER(LEFT(B606,4)+1-1) -> FALSE | D606: =IF(C606,LEFT(B606,10),D605)+1-1 -> 0
A607: SHORT | B607: XAGUSD - silver peaked then pulled back, technicals point to correction. | C607: =ISNUMBER(LEFT(B607,4)+1-1) -> FALSE | D607: =IF(C607,LEFT(B607,10),D606)+1-1 -> 0
A608: SHORT | B608: USDJPY - FX showing US dollar capped and mixed risk appetite - short yen weakness. | C608: =ISNUMBER(LEFT(B608,4)+1-1) -> FALSE | D608: =IF(C608,LEFT(B608,10),D607)+1-1 -> 0
A609: SHORT | B609: VIX - volatility index extremely low with asymmetric upside risk, anticipate repricing. | C609: =ISNUMBER(LEFT(B609,4)+1-1) -> FALSE | D609: =IF(C609,LEFT(B609,10),D608)+1-1 -> 0
A610: SHORT | B610: 0 | C610: =ISNUMBER(LEFT(B610,4)+1-1) -> TRUE | D610: =IF(C610,LEFT(B610,10),D609)+1-1 -> 0
A611: SHORT | B611: isn't vix then should be Long if low | C611: =ISNUMBER(LEFT(B611,4)+1-1) -> FALSE | D611: =IF(C611,LEFT(B611,10),D610)+1-1 -> 0
A612: SHORT | B612: Correct. | C612: =ISNUMBER(LEFT(B612,4)+1-1) -> FALSE | D612: =IF(C612,LEFT(B612,10),D611)+1-1 -> 0
A613: SHORT | B613: If VIX is low, the directional trade is LONG VIX, not short. | C613: =ISNUMBER(LEFT(B613,4)+1-1) -> FALSE | D613: =IF(C613,LEFT(B613,10),D612)+1-1 -> 0
A614: SHORT | B614: Low implied volatility implies asymmetric upside risk and mean reversion favors expansion. | C614: =ISNUMBER(LEFT(B614,4)+1-1) -> FALSE | D614: =IF(C614,LEFT(B614,10),D613)+1-1 -> 0
A615: SHORT | B615: Shorting VIX only makes sense after a volatility spike, not at compressed levels. | C615: =ISNUMBER(LEFT(B615,4)+1-1) -> FALSE | D615: =IF(C615,LEFT(B615,10),D614)+1-1 -> 0
A616: SHORT | B616: 0 | C616: =ISNUMBER(LEFT(B616,4)+1-1) -> TRUE | D616: =IF(C616,LEFT(B616,10),D615)+1-1 -> 0
A617: SHORT | B617: Conclusion: VIX was misclassified. A low-VIX regime invalidates it as a short candidate. | C617: =ISNUMBER(LEFT(B617,4)+1-1) -> FALSE | D617: =IF(C617,LEFT(B617,10),D616)+1-1 -> 0
A618: SHORT | B618: 0 | C618: =ISNUMBER(LEFT(B618,4)+1-1) -> TRUE | D618: =IF(C618,LEFT(B618,10),D617)+1-1 -> 0
A619: SHORT | B619: Updated memories | C619: =ISNUMBER(LEFT(B619,4)+1-1) -> FALSE | D619: =IF(C619,LEFT(B619,10),D618)+1-1 -> 0
A620: SHORT | B620: Yes. Two errors. | C620: =ISNUMBER(LEFT(B620,4)+1-1) -> FALSE | D620: =IF(C620,LEFT(B620,10),D619)+1-1 -> 0
A621: SHORT | B621: 0 | C621: =ISNUMBER(LEFT(B621,4)+1-1) -> TRUE | D621: =IF(C621,LEFT(B621,10),D620)+1-1 -> 0
A622: SHORT | B622: 1. VIX | C622: =ISNUMBER(LEFT(B622,4)+1-1) -> FALSE | D622: =IF(C622,LEFT(B622,10),D621)+1-1 -> 0
A623: SHORT | B623: Wrong side. Low VIX implies LONG volatility, not short. Short VIX only after spikes. | C623: =ISNUMBER(LEFT(B623,4)+1-1) -> FALSE | D623: =IF(C623,LEFT(B623,10),D622)+1-1 -> 0
A624: SHORT | B624: 0 | C624: =ISNUMBER(LEFT(B624,4)+1-1) -> TRUE | D624: =IF(C624,LEFT(B624,10),D623)+1-1 -> 0
A625: SHORT | B625: 2. USDJPY | C625: =ISNUMBER(LEFT(B625,4)+1-1) -> FALSE | D625: =IF(C625,LEFT(B625,10),D624)+1-1 -> 0
A626: SHORT | B626: Short USDJPY equals long JPY strength. If expecting yen weakness, the position should be long USDJPY. | C626: =ISNUMBER(LEFT(B626,4)+1-1) -> FALSE | D626: =IF(C626,LEFT(B626,10),D625)+1-1 -> 0
A627: SHORT | B627: All other shorts were directionally consistent. | C627: =ISNUMBER(LEFT(B627,4)+1-1) -> FALSE | D627: =IF(C627,LEFT(B627,10),D626)+1-1 -> 0
A628: SHORT | B628: 0 | C628: =ISNUMBER(LEFT(B628,4)+1-1) -> TRUE | D628: =IF(C628,LEFT(B628,10),D627)+1-1 -> 0
A629: SHORT | B629: 2026‑01‑06 / 08:15 - Tuesday | C629: =ISNUMBER(LEFT(B629,4)+1-1) -> TRUE | D629: =IF(C629,LEFT(B629,10),D628)+1-1 -> #VALUE!
A630: SHORT | B630: 0 | C630: =ISNUMBER(LEFT(B630,4)+1-1) -> TRUE | D630: =IF(C630,LEFT(B630,10),D629)+1-1 -> 0
A631: SHORT | B631: SENSEX (NSE) – Indian benchmark weakening with key stocks lagging, risk‑off setup. | C631: =ISNUMBER(LEFT(B631,4)+1-1) -> FALSE | D631: =IF(C631,LEFT(B631,10),D630)+1-1 -> 0
A632: SHORT | B632: EUR/USD – pair below key resistance, short bias as downside persists. | C632: =ISNUMBER(LEFT(B632,4)+1-1) -> FALSE | D632: =IF(C632,LEFT(B632,10),D631)+1-1 -> 0
A633: SHORT | B633: SPY – broad US equity indices showing technical breakdown and bearish signals. | C633: =ISNUMBER(LEFT(B633,4)+1-1) -> FALSE | D633: =IF(C633,LEFT(B633,10),D632)+1-1 -> 0
A634: SHORT | B634: 0 | C634: =ISNUMBER(LEFT(B634,4)+1-1) -> TRUE | D634: =IF(C634,LEFT(B634,10),D633)+1-1 -> 0
A635: SHORT | B635: 2026‑01‑07 / 08:15 - Wednesday | C635: =ISNUMBER(LEFT(B635,4)+1-1) -> TRUE | D635: =IF(C635,LEFT(B635,10),D634)+1-1 -> #VALUE!
A636: SHORT | B636: 0 | C636: =ISNUMBER(LEFT(B636,4)+1-1) -> TRUE | D636: =IF(C636,LEFT(B636,10),D635)+1-1 -> 0
A637: SHORT | B637: SILVER (XAGUSD) - price downtrend confirmed below key levels with bearish momentum and break lower support. | C637: =ISNUMBER(LEFT(B637,4)+1-1) -> FALSE | D637: =IF(C637,LEFT(B637,10),D636)+1-1 -> 0
A638: SHORT | B638: NIKKEI225 - Asian index shows mixed macro sentiment and Asian energy stocks lag, downside tilt. | C638: =ISNUMBER(LEFT(B638,4)+1-1) -> FALSE | D638: =IF(C638,LEFT(B638,10),D637)+1-1 -> 0
A639: SHORT | B639: EURUSD - technical indicators in short frames signal bearish continuation after resistance rejection. | C639: =ISNUMBER(LEFT(B639,4)+1-1) -> FALSE | D639: =IF(C639,LEFT(B639,10),D638)+1-1 -> 0
A640: SHORT | B640: 0 | C640: =ISNUMBER(LEFT(B640,4)+1-1) -> TRUE | D640: =IF(C640,LEFT(B640,10),D639)+1-1 -> 0
A641: SHORT | B641: 2026‑01‑08 / 08:16 - Thursday | C641: =ISNUMBER(LEFT(B641,4)+1-1) -> TRUE | D641: =IF(C641,LEFT(B641,10),D640)+1-1 -> #VALUE!
A642: SHORT | B642: 0 | C642: =ISNUMBER(LEFT(B642,4)+1-1) -> TRUE | D642: =IF(C642,LEFT(B642,10),D641)+1-1 -> 0
A643: SHORT | B643: SPY – broad US equity futures showing weakness and technical pullback after rally exhaustion. | C643: =ISNUMBER(LEFT(B643,4)+1-1) -> FALSE | D643: =IF(C643,LEFT(B643,10),D642)+1-1 -> 0
A644: SHORT | B644: XAGUSD – silver facing significant selling pressure from annual commodity rebalancing. | C644: =ISNUMBER(LEFT(B644,4)+1-1) -> FALSE | D644: =IF(C644,LEFT(B644,10),D643)+1-1 -> 0
A645: SHORT | B645: DAX – European index retreating from short‑term resistance with broad risk‑off price action. | C645: =ISNUMBER(LEFT(B645,4)+1-1) -> FALSE | D645: =IF(C645,LEFT(B645,10),D644)+1-1 -> 0
A646: SHORT | B646: 0 | C646: =ISNUMBER(LEFT(B646,4)+1-1) -> TRUE | D646: =IF(C646,LEFT(B646,10),D645)+1-1 -> 0
A647: SHORT | B647: 2026-01-12 / 08:16 - Monday | C647: =ISNUMBER(LEFT(B647,4)+1-1) -> TRUE | D647: =IF(C647,LEFT(B647,10),D646)+1-1 -> 46034
A648: SHORT | B648: 0 | C648: =ISNUMBER(LEFT(B648,4)+1-1) -> TRUE | D648: =IF(C648,LEFT(B648,10),D647)+1-1 -> 0
A649: SHORT | B649: SPY – Index showing pre-market weakness from prior pullback and macro uncertainty. | C649: =ISNUMBER(LEFT(B649,4)+1-1) -> FALSE | D649: =IF(C649,LEFT(B649,10),D648)+1-1 -> 0
A650: SHORT | B650: AAPL – Large cap tech under pressure and momentum weak vs peers. | C650: =ISNUMBER(LEFT(B650,4)+1-1) -> FALSE | D650: =IF(C650,LEFT(B650,10),D649)+1-1 -> 0
A651: SHORT | B651: NQ=F – Nasdaq futures showing risk-off technical bias and sector rotation out of growth. | C651: =ISNUMBER(LEFT(B651,4)+1-1) -> FALSE | D651: =IF(C651,LEFT(B651,10),D650)+1-1 -> 0
A652: SHORT | B652: 0 | C652: =ISNUMBER(LEFT(B652,4)+1-1) -> TRUE | D652: =IF(C652,LEFT(B652,10),D651)+1-1 -> 0
A653: SHORT | B653: 2026-01-12 / 08:15 - Monday | C653: =ISNUMBER(LEFT(B653,4)+1-1) -> TRUE | D653: =IF(C653,LEFT(B653,10),D652)+1-1 -> 46034
A654: SHORT | B654: 0 | C654: =ISNUMBER(LEFT(B654,4)+1-1) -> TRUE | D654: =IF(C654,LEFT(B654,10),D653)+1-1 -> 0
A655: SHORT | B655: N225 - Nikkei 225 futures (momentum fading near record highs with pullback risk) | C655: =ISNUMBER(LEFT(B655,4)+1-1) -> FALSE | D655: =IF(C655,LEFT(B655,10),D654)+1-1 -> 0
A656: SHORT | B656: BRN=F - Brent crude oil futures (price under pressure amid supply and geopolitical tensions) | C656: =ISNUMBER(LEFT(B656,4)+1-1) -> FALSE | D656: =IF(C656,LEFT(B656,10),D655)+1-1 -> 0
A657: SHORT | B657: INDU - Dow Jones Industrial Average futures (broad market vulnerability despite recent highs) | C657: =ISNUMBER(LEFT(B657,4)+1-1) -> FALSE | D657: =IF(C657,LEFT(B657,10),D656)+1-1 -> 0
A658: SHORT | B658: 0 | C658: =ISNUMBER(LEFT(B658,4)+1-1) -> TRUE | D658: =IF(C658,LEFT(B658,10),D657)+1-1 -> 0
A659: SHORT | B659: 2026‑01‑12 / 08:15 - Monday | C659: =ISNUMBER(LEFT(B659,4)+1-1) -> TRUE | D659: =IF(C659,LEFT(B659,10),D658)+1-1 -> #VALUE!
A660: SHORT | B660: 0 | C660: =ISNUMBER(LEFT(B660,4)+1-1) -> TRUE | D660: =IF(C660,LEFT(B660,10),D659)+1-1 -> 0
A661: SHORT | B661: ABF.L – Associated British Foods (profit warning, shares down sharply on weak Primark & U.S. demand) | C661: =ISNUMBER(LEFT(B661,4)+1-1) -> FALSE | D661: =IF(C661,LEFT(B661,10),D660)+1-1 -> 0
A662: SHORT | B662: GRG.L – Greggs PLC (flat profit outlook, subdued consumer confidence pressure) | C662: =ISNUMBER(LEFT(B662,4)+1-1) -> FALSE | D662: =IF(C662,LEFT(B662,10),D661)+1-1 -> 0
A663: SHORT | B663: USD/SEK – US Dollar vs Swedish Krona (USD strength driving emerging market FX weakness) | C663: =ISNUMBER(LEFT(B663,4)+1-1) -> FALSE | D663: =IF(C663,LEFT(B663,10),D662)+1-1 -> 0
A664: SHORT | B664: 0 | C664: =ISNUMBER(LEFT(B664,4)+1-1) -> TRUE | D664: =IF(C664,LEFT(B664,10),D663)+1-1 -> 0
A665: SHORT | B665: 2026‑01‑12 / 08:16 - Monday | C665: =ISNUMBER(LEFT(B665,4)+1-1) -> TRUE | D665: =IF(C665,LEFT(B665,10),D664)+1-1 -> #VALUE!
A666: SHORT | B666: 0 | C666: =ISNUMBER(LEFT(B666,4)+1-1) -> TRUE | D666: =IF(C666,LEFT(B666,10),D665)+1-1 -> 0
A667: SHORT | B667: ES=F - S&P 500 futures (morning weakness on political/market instability, bearish short bias) | C667: =ISNUMBER(LEFT(B667,4)+1-1) -> FALSE | D667: =IF(C667,LEFT(B667,10),D666)+1-1 -> 0
A668: SHORT | B668: AUDUSD - Australian dollar (BofA signals near‑term downside bias in FX) | C668: =ISNUMBER(LEFT(B668,4)+1-1) -> FALSE | D668: =IF(C668,LEFT(B668,10),D667)+1-1 -> 0
A669: SHORT | B669: EURUSD - Euro vs US Dollar (crowded long positioning and technical corrective risk) | C669: =ISNUMBER(LEFT(B669,4)+1-1) -> FALSE | D669: =IF(C669,LEFT(B669,10),D668)+1-1 -> 0
A670: SHORT | B670: 0 | C670: =ISNUMBER(LEFT(B670,4)+1-1) -> TRUE | D670: =IF(C670,LEFT(B670,10),D669)+1-1 -> 0
A671: SHORT | B671: 2026‑01‑13 / 08:16 - Tuesday | C671: =ISNUMBER(LEFT(B671,4)+1-1) -> TRUE | D671: =IF(C671,LEFT(B671,10),D670)+1-1 -> #VALUE!
A672: SHORT | B672: 0 | C672: =ISNUMBER(LEFT(B672,4)+1-1) -> TRUE | D672: =IF(C672,LEFT(B672,10),D671)+1-1 -> 0
A673: SHORT | B673: SPX500 (S&P 500 futures) - U.S. stock futures weak on risk‑off flows after Powell Fed probe and ahead of CPI, bearish bias. | C673: =ISNUMBER(LEFT(B673,4)+1-1) -> FALSE | D673: =IF(C673,LEFT(B673,10),D672)+1-1 -> 0
A674: SHORT | B674: USD/JPY - Yen weakness extreme but corrective risk rising as carry unwinds into key data, topside rejection pressure. | C674: =ISNUMBER(LEFT(B674,4)+1-1) -> FALSE | D674: =IF(C674,LEFT(B674,10),D673)+1-1 -> 0
A675: SHORT | B675: NIFTY50 (India index) - Sensex/Nifty under pressure with worst start to year in decade, indicating broader risk sentiment. | C675: =ISNUMBER(LEFT(B675,4)+1-1) -> FALSE | D675: =IF(C675,LEFT(B675,10),D674)+1-1 -> 0
...

Sheet Sheet5
A1: Is date? | B1: TRUE
A3: Count of Date | B3: Column Labels
A4: Row Labels | B4: longall | C4: longeq | D4: short | E4: Grand Total
A5: #VALUE! | B5: 8 | D5: 17 | E5: 25
A6: 45995 | C6: 1 | E6: 1
A7: 45996 | C7: 2 | E7: 2
A8: 46026 | D8: 1 | E8: 1
A9: 46027 | B9: 1 | E9: 1
A10: 46029 | B10: 1 | E10: 1
A11: 46031 | B11: 1 | E11: 1
A12: 46032 | B12: 1 | E12: 1
A13: 46033 | B13: 1 | E13: 1
A14: 46034 | D14: 2 | E14: 2
A15: 46037 | B15: 1 | E15: 1
A16: 46038 | B16: 1 | E16: 1
A17: 46040 | B17: 1 | D17: 1 | E17: 2
A18: 46041 | B18: 2 | D18: 1 | E18: 3
A19: 46042 | B19: 1 | D19: 1 | E19: 2
A20: 46043 | D20: 1 | E20: 1
A21: 46044 | B21: 1 | E21: 1
A22: 46046 | B22: 1 | E22: 1
A23: 46047 | B23: 1 | E23: 1
A24: 46048 | B24: 1 | E24: 1
A25: 46050 | D25: 1 | E25: 1
A26: 46051 | D26: 1 | E26: 1
A27: 46160 | B27: 1 | C27: 1 | D27: 1 | E27: 3
A28: 46161 | B28: 1 | C28: 1 | D28: 1 | E28: 3
A29: Grand Total | B29: 25 | C29: 5 | D29: 28 | E29: 58

Sheet threesheets merge
A1: disable? | B1: strategy | D1: Is date? | E1: Date | F1: Rec 1 | G1: Rec 2 | H1: Rec 3 | I1: Rec 4 | J1: Rec 5
B2: longeq | C2: 2025-12-04 / 14:05 - Thursday | D2: =ISNUMBER(LEFT(C2,4)+1-1) -> TRUE | E2: =IF(D2,LEFT(C2,10),E1)+1-1 -> 45995 | F2: =C4 -> Recs: | G2: =C5 -> MRVL – Marvell Technology, Inc. | H2: =C6 -> RIO – Rio Tinto plc | I2: =C7 -> STLA – Stellantis N.V. | J2: =C8 -> TD – The Toronto-Dominion Bank
B3: longeq | D3: =ISNUMBER(LEFT(C3,4)+1-1) -> FALSE | E3: =IF(D3,LEFT(C3,10),E2)+1-1 -> 45995 | F3: =C5 -> MRVL – Marvell Technology, Inc. | G3: =C6 -> RIO – Rio Tinto plc | H3: =C7 -> STLA – Stellantis N.V. | I3: =C8 -> TD – The Toronto-Dominion Bank | J3: =C9 -> CRDO – Credo Technology Group Holding Ltd.
B4: longeq | C4: Recs: | D4: =ISNUMBER(LEFT(C4,4)+1-1) -> FALSE | E4: =IF(D4,LEFT(C4,10),E3)+1-1 -> 45995 | F4: =C6 -> RIO – Rio Tinto plc | G4: =C7 -> STLA – Stellantis N.V. | H4: =C8 -> TD – The Toronto-Dominion Bank | I4: =C9 -> CRDO – Credo Technology Group Holding Ltd. | J4: =C10 -> 0
B5: longeq | C5: MRVL – Marvell Technology, Inc. | D5: =ISNUMBER(LEFT(C5,4)+1-1) -> FALSE | E5: =IF(D5,LEFT(C5,10),E4)+1-1 -> 45995 | F5: =C7 -> STLA – Stellantis N.V. | G5: =C8 -> TD – The Toronto-Dominion Bank | H5: =C9 -> CRDO – Credo Technology Group Holding Ltd. | I5: =C10 -> 0 | J5: =C11 -> Prev days return S&P500 +0.30%
B6: longeq | C6: RIO – Rio Tinto plc | D6: =ISNUMBER(LEFT(C6,4)+1-1) -> FALSE | E6: =IF(D6,LEFT(C6,10),E5)+1-1 -> 45995 | F6: =C8 -> TD – The Toronto-Dominion Bank | G6: =C9 -> CRDO – Credo Technology Group Holding Ltd. | H6: =C10 -> 0 | I6: =C11 -> Prev days return S&P500 +0.30% | J6: =C12 -> 0
B7: longeq | C7: STLA – Stellantis N.V. | D7: =ISNUMBER(LEFT(C7,4)+1-1) -> FALSE | E7: =IF(D7,LEFT(C7,10),E6)+1-1 -> 45995 | F7: =C9 -> CRDO – Credo Technology Group Holding Ltd. | G7: =C10 -> 0 | H7: =C11 -> Prev days return S&P500 +0.30% | I7: =C12 -> 0 | J7: =C13 -> please set this up as a task.
B8: longeq | C8: TD – The Toronto-Dominion Bank | D8: =ISNUMBER(LEFT(C8,4)+1-1) -> FALSE | E8: =IF(D8,LEFT(C8,10),E7)+1-1 -> 45995 | F8: =C10 -> 0 | G8: =C11 -> Prev days return S&P500 +0.30% | H8: =C12 -> 0 | I8: =C13 -> please set this up as a task. | J8: =C14 -> Produce daily short-term EQ trade recommendations
B9: longeq | C9: CRDO – Credo Technology Group Holding Ltd. | D9: =ISNUMBER(LEFT(C9,4)+1-1) -> FALSE | E9: =IF(D9,LEFT(C9,10),E8)+1-1 -> 45995 | F9: =C11 -> Prev days return S&P500 +0.30% | G9: =C12 -> 0 | H9: =C13 -> please set this up as a task. | I9: =C14 -> Produce daily short-term EQ trade recommendations | J9: =C15 -> Daily at 3:30 PM
B10: longeq | D10: =ISNUMBER(LEFT(C10,4)+1-1) -> FALSE | E10: =IF(D10,LEFT(C10,10),E9)+1-1 -> 45995 | F10: =C12 -> 0 | G10: =C13 -> please set this up as a task. | H10: =C14 -> Produce daily short-term EQ trade recommendations | I10: =C15 -> Daily at 3:30 PM | J10: =C16 -> 0
B11: longeq | C11: Prev days return S&P500 +0.30% | D11: =ISNUMBER(LEFT(C11,4)+1-1) -> FALSE | E11: =IF(D11,LEFT(C11,10),E10)+1-1 -> 45995 | F11: =C13 -> please set this up as a task. | G11: =C14 -> Produce daily short-term EQ trade recommendations | H11: =C15 -> Daily at 3:30 PM | I11: =C16 -> 0 | J11: =C17 -> Set.
B12: longeq | D12: =ISNUMBER(LEFT(C12,4)+1-1) -> FALSE | E12: =IF(D12,LEFT(C12,10),E11)+1-1 -> 45995 | F12: =C14 -> Produce daily short-term EQ trade recommendations | G12: =C15 -> Daily at 3:30 PM | H12: =C16 -> 0 | I12: =C17 -> Set. | J12: =C18 -> 0
B13: longeq | C13: please set this up as a task. | D13: =ISNUMBER(LEFT(C13,4)+1-1) -> FALSE | E13: =IF(D13,LEFT(C13,10),E12)+1-1 -> 45995 | F13: =C15 -> Daily at 3:30 PM | G13: =C16 -> 0 | H13: =C17 -> Set. | I13: =C18 -> 0 | J13: =C19 -> thanks! Please re-run as a test
B14: longeq | C14: Produce daily short-term EQ trade recommendations | D14: =ISNUMBER(LEFT(C14,4)+1-1) -> FALSE | E14: =IF(D14,LEFT(C14,10),E13)+1-1 -> 45995 | F14: =C16 -> 0 | G14: =C17 -> Set. | H14: =C18 -> 0 | I14: =C19 -> thanks! Please re-run as a test | J14: =C20 -> 0
B15: longeq | C15: Daily at 3:30 PM | D15: =ISNUMBER(LEFT(C15,4)+1-1) -> FALSE | E15: =IF(D15,LEFT(C15,10),E14)+1-1 -> 45995 | F15: =C17 -> Set. | G15: =C18 -> 0 | H15: =C19 -> thanks! Please re-run as a test | I15: =C20 -> 0 | J15: =C21 -> 2025-12-05 / 09:00 - Friday
B16: longeq | D16: =ISNUMBER(LEFT(C16,4)+1-1) -> FALSE | E16: =IF(D16,LEFT(C16,10),E15)+1-1 -> 45995 | F16: =C18 -> 0 | G16: =C19 -> thanks! Please re-run as a test | H16: =C20 -> 0 | I16: =C21 -> 2025-12-05 / 09:00 - Friday | J16: =C22 -> 0
B17: longeq | C17: Set. | D17: =ISNUMBER(LEFT(C17,4)+1-1) -> FALSE | E17: =IF(D17,LEFT(C17,10),E16)+1-1 -> 45995 | F17: =C19 -> thanks! Please re-run as a test | G17: =C20 -> 0 | H17: =C21 -> 2025-12-05 / 09:00 - Friday | I17: =C22 -> 0 | J17: =C23 -> Recs:
B18: longeq | D18: =ISNUMBER(LEFT(C18,4)+1-1) -> FALSE | E18: =IF(D18,LEFT(C18,10),E17)+1-1 -> 45995 | F18: =C20 -> 0 | G18: =C21 -> 2025-12-05 / 09:00 - Friday | H18: =C22 -> 0 | I18: =C23 -> Recs: | J18: =C24 -> XOM – Exxon Mobil Corporation
B19: longeq | C19: thanks! Please re-run as a test | D19: =ISNUMBER(LEFT(C19,4)+1-1) -> FALSE | E19: =IF(D19,LEFT(C19,10),E18)+1-1 -> 45995 | F19: =C21 -> 2025-12-05 / 09:00 - Friday | G19: =C22 -> 0 | H19: =C23 -> Recs: | I19: =C24 -> XOM – Exxon Mobil Corporation | J19: =C25 -> FCX – Freeport-McMoRan Inc.
B20: longeq | D20: =ISNUMBER(LEFT(C20,4)+1-1) -> FALSE | E20: =IF(D20,LEFT(C20,10),E19)+1-1 -> 45995 | F20: =C22 -> 0 | G20: =C23 -> Recs: | H20: =C24 -> XOM – Exxon Mobil Corporation | I20: =C25 -> FCX – Freeport-McMoRan Inc. | J20: =C26 -> AIR – Airbus SE
B21: longeq | C21: 2025-12-05 / 09:00 - Friday | D21: =ISNUMBER(LEFT(C21,4)+1-1) -> TRUE | E21: =IF(D21,LEFT(C21,10),E20)+1-1 -> 45996 | F21: =C23 -> Recs: | G21: =C24 -> XOM – Exxon Mobil Corporation | H21: =C25 -> FCX – Freeport-McMoRan Inc. | I21: =C26 -> AIR – Airbus SE | J21: =C27 -> BTI – British American Tobacco plc
B22: longeq | D22: =ISNUMBER(LEFT(C22,4)+1-1) -> FALSE | E22: =IF(D22,LEFT(C22,10),E21)+1-1 -> 45996 | F22: =C24 -> XOM – Exxon Mobil Corporation | G22: =C25 -> FCX – Freeport-McMoRan Inc. | H22: =C26 -> AIR – Airbus SE | I22: =C27 -> BTI – British American Tobacco plc | J22: =C28 -> BHP – BHP Group Ltd.
B23: longeq | C23: Recs: | D23: =ISNUMBER(LEFT(C23,4)+1-1) -> FALSE | E23: =IF(D23,LEFT(C23,10),E22)+1-1 -> 45996 | F23: =C25 -> FCX – Freeport-McMoRan Inc. | G23: =C26 -> AIR – Airbus SE | H23: =C27 -> BTI – British American Tobacco plc | I23: =C28 -> BHP – BHP Group Ltd. | J23: =C29 -> 0
B24: longeq | C24: XOM – Exxon Mobil Corporation | D24: =ISNUMBER(LEFT(C24,4)+1-1) -> FALSE | E24: =IF(D24,LEFT(C24,10),E23)+1-1 -> 45996 | F24: =C26 -> AIR – Airbus SE | G24: =C27 -> BTI – British American Tobacco plc | H24: =C28 -> BHP – BHP Group Ltd. | I24: =C29 -> 0 | J24: =C30 -> Prev days return S&P500 +0.30%
B25: longeq | C25: FCX – Freeport-McMoRan Inc. | D25: =ISNUMBER(LEFT(C25,4)+1-1) -> FALSE | E25: =IF(D25,LEFT(C25,10),E24)+1-1 -> 45996 | F25: =C27 -> BTI – British American Tobacco plc | G25: =C28 -> BHP – BHP Group Ltd. | H25: =C29 -> 0 | I25: =C30 -> Prev days return S&P500 +0.30% | J25: =C31 -> 0
B26: longeq | C26: AIR – Airbus SE | D26: =ISNUMBER(LEFT(C26,4)+1-1) -> FALSE | E26: =IF(D26,LEFT(C26,10),E25)+1-1 -> 45996 | F26: =C28 -> BHP – BHP Group Ltd. | G26: =C29 -> 0 | H26: =C30 -> Prev days return S&P500 +0.30% | I26: =C31 -> 0 | J26: =C32 -> I've changed the task. please run the task as if it would run tomorrow
B27: longeq | C27: BTI – British American Tobacco plc | D27: =ISNUMBER(LEFT(C27,4)+1-1) -> FALSE | E27: =IF(D27,LEFT(C27,10),E26)+1-1 -> 45996 | F27: =C29 -> 0 | G27: =C30 -> Prev days return S&P500 +0.30% | H27: =C31 -> 0 | I27: =C32 -> I've changed the task. please run the task as if it would run tomorrow | J27: =C33 -> 0
B28: longeq | C28: BHP – BHP Group Ltd. | D28: =ISNUMBER(LEFT(C28,4)+1-1) -> FALSE | E28: =IF(D28,LEFT(C28,10),E27)+1-1 -> 45996 | F28: =C30 -> Prev days return S&P500 +0.30% | G28: =C31 -> 0 | H28: =C32 -> I've changed the task. please run the task as if it would run tomorrow | I28: =C33 -> 0 | J28: =C34 -> 2025-12-05 / 09:00 - Friday
B29: longeq | D29: =ISNUMBER(LEFT(C29,4)+1-1) -> FALSE | E29: =IF(D29,LEFT(C29,10),E28)+1-1 -> 45996 | F29: =C31 -> 0 | G29: =C32 -> I've changed the task. please run the task as if it would run tomorrow | H29: =C33 -> 0 | I29: =C34 -> 2025-12-05 / 09:00 - Friday | J29: =C35 -> 0
B30: longeq | C30: Prev days return S&P500 +0.30% | D30: =ISNUMBER(LEFT(C30,4)+1-1) -> FALSE | E30: =IF(D30,LEFT(C30,10),E29)+1-1 -> 45996 | F30: =C32 -> I've changed the task. please run the task as if it would run tomorrow | G30: =C33 -> 0 | H30: =C34 -> 2025-12-05 / 09:00 - Friday | I30: =C35 -> 0 | J30: =C36 -> Recs:
B31: longeq | D31: =ISNUMBER(LEFT(C31,4)+1-1) -> FALSE | E31: =IF(D31,LEFT(C31,10),E30)+1-1 -> 45996 | F31: =C33 -> 0 | G31: =C34 -> 2025-12-05 / 09:00 - Friday | H31: =C35 -> 0 | I31: =C36 -> Recs: | J31: =C37 -> XOM – Exxon Mobil Corporation
B32: longeq | C32: I've changed the task. please run the task as if it would run tomorrow | D32: =ISNUMBER(LEFT(C32,4)+1-1) -> FALSE | E32: =IF(D32,LEFT(C32,10),E31)+1-1 -> 45996 | F32: =C34 -> 2025-12-05 / 09:00 - Friday | G32: =C35 -> 0 | H32: =C36 -> Recs: | I32: =C37 -> XOM – Exxon Mobil Corporation | J32: =C38 -> FCX – Freeport-McMoRan Inc.
B33: longeq | D33: =ISNUMBER(LEFT(C33,4)+1-1) -> FALSE | E33: =IF(D33,LEFT(C33,10),E32)+1-1 -> 45996 | F33: =C35 -> 0 | G33: =C36 -> Recs: | H33: =C37 -> XOM – Exxon Mobil Corporation | I33: =C38 -> FCX – Freeport-McMoRan Inc. | J33: =C39 -> AIR – Airbus SE
B34: longeq | C34: 2025-12-05 / 09:00 - Friday | D34: =ISNUMBER(LEFT(C34,4)+1-1) -> TRUE | E34: =IF(D34,LEFT(C34,10),E33)+1-1 -> 45996 | F34: =C36 -> Recs: | G34: =C37 -> XOM – Exxon Mobil Corporation | H34: =C38 -> FCX – Freeport-McMoRan Inc. | I34: =C39 -> AIR – Airbus SE | J34: =C40 -> BTI – British American Tobacco plc
B35: longeq | D35: =ISNUMBER(LEFT(C35,4)+1-1) -> FALSE | E35: =IF(D35,LEFT(C35,10),E34)+1-1 -> 45996 | F35: =C37 -> XOM – Exxon Mobil Corporation | G35: =C38 -> FCX – Freeport-McMoRan Inc. | H35: =C39 -> AIR – Airbus SE | I35: =C40 -> BTI – British American Tobacco plc | J35: =C41 -> BHP – BHP Group Ltd.
B36: longeq | C36: Recs: | D36: =ISNUMBER(LEFT(C36,4)+1-1) -> FALSE | E36: =IF(D36,LEFT(C36,10),E35)+1-1 -> 45996 | F36: =C38 -> FCX – Freeport-McMoRan Inc. | G36: =C39 -> AIR – Airbus SE | H36: =C40 -> BTI – British American Tobacco plc | I36: =C41 -> BHP – BHP Group Ltd. | J36: =C42 -> 0
B37: longeq | C37: XOM – Exxon Mobil Corporation | D37: =ISNUMBER(LEFT(C37,4)+1-1) -> FALSE | E37: =IF(D37,LEFT(C37,10),E36)+1-1 -> 45996 | F37: =C39 -> AIR – Airbus SE | G37: =C40 -> BTI – British American Tobacco plc | H37: =C41 -> BHP – BHP Group Ltd. | I37: =C42 -> 0 | J37: =C43 -> Prev days return S&P500 +0.30%
B38: longeq | C38: FCX – Freeport-McMoRan Inc. | D38: =ISNUMBER(LEFT(C38,4)+1-1) -> FALSE | E38: =IF(D38,LEFT(C38,10),E37)+1-1 -> 45996 | F38: =C40 -> BTI – British American Tobacco plc | G38: =C41 -> BHP – BHP Group Ltd. | H38: =C42 -> 0 | I38: =C43 -> Prev days return S&P500 +0.30% | J38: =C44 -> 0
B39: longeq | C39: AIR – Airbus SE | D39: =ISNUMBER(LEFT(C39,4)+1-1) -> FALSE | E39: =IF(D39,LEFT(C39,10),E38)+1-1 -> 45996 | F39: =C41 -> BHP – BHP Group Ltd. | G39: =C42 -> 0 | H39: =C43 -> Prev days return S&P500 +0.30% | I39: =C44 -> 0 | J39: =C45 -> I have changed the task to include prev. days returns. can't you see it?
B40: longeq | C40: BTI – British American Tobacco plc | D40: =ISNUMBER(LEFT(C40,4)+1-1) -> FALSE | E40: =IF(D40,LEFT(C40,10),E39)+1-1 -> 45996 | F40: =C42 -> 0 | G40: =C43 -> Prev days return S&P500 +0.30% | H40: =C44 -> 0 | I40: =C45 -> I have changed the task to include prev. days returns. can't you see it? | J40: =C46 -> 0
B41: longeq | C41: BHP – BHP Group Ltd. | D41: =ISNUMBER(LEFT(C41,4)+1-1) -> FALSE | E41: =IF(D41,LEFT(C41,10),E40)+1-1 -> 45996 | F41: =C43 -> Prev days return S&P500 +0.30% | G41: =C44 -> 0 | H41: =C45 -> I have changed the task to include prev. days returns. can't you see it? | I41: =C46 -> 0 | J41: =C47 -> Your new task definition is not visible in this thread. Automations do not update themselves unless you explicitly request an update. State the exact revised instructions you want the task to follow and I will modify the automation accordingly.
B42: longeq | D42: =ISNUMBER(LEFT(C42,4)+1-1) -> FALSE | E42: =IF(D42,LEFT(C42,10),E41)+1-1 -> 45996 | F42: =C44 -> 0 | G42: =C45 -> I have changed the task to include prev. days returns. can't you see it? | H42: =C46 -> 0 | I42: =C47 -> Your new task definition is not visible in this thread. Automations do not update themselves unless you explicitly request an update. State the exact revised instructions you want the task to follow and I will modify the automation accordingly. | J42: =C48 -> 0
B43: longeq | C43: Prev days return S&P500 +0.30% | D43: =ISNUMBER(LEFT(C43,4)+1-1) -> FALSE | E43: =IF(D43,LEFT(C43,10),E42)+1-1 -> 45996 | F43: =C45 -> I have changed the task to include prev. days returns. can't you see it? | G43: =C46 -> 0 | H43: =C47 -> Your new task definition is not visible in this thread. Automations do not update themselves unless you explicitly request an update. State the exact revised instructions you want the task to follow and I will modify the automation accordingly. | I43: =C48 -> 0 | J43: =C49 -> For a short term trade, to be opened in the morning and closed at end of day, search for the latest major global news. Recommend EXACTLY 5 BUY tickers for short-term trade based on fresh catalysts and momentum. Then followup with previous days returns, avg day return and daily SP500 return. Start with one line containing the local date and day of week in Stockholm time formatted exactly as: YYYY-MM-DD / HH:MM - Monday Recs: TICKER – Company TICKER – Company TICKER – Company TICKER – Company TICKER – Company Perf (prev recs): TICKER +X.XX% TICKER -X.XX% TICKER +X.XX% TICKER +X.XX% TICKER -X.XX% Avg +X.XX% Prev days return S&P500 +X.XX%
B44: longeq | D44: =ISNUMBER(LEFT(C44,4)+1-1) -> FALSE | E44: =IF(D44,LEFT(C44,10),E43)+1-1 -> 45996 | F44: =C46 -> 0 | G44: =C47 -> Your new task definition is not visible in this thread. Automations do not update themselves unless you explicitly request an update. State the exact revised instructions you want the task to follow and I will modify the automation accordingly. | H44: =C48 -> 0 | I44: =C49 -> For a short term trade, to be opened in the morning and closed at end of day, search for the latest major global news. Recommend EXACTLY 5 BUY tickers for short-term trade based on fresh catalysts and momentum. Then followup with previous days returns, avg day return and daily SP500 return. Start with one line containing the local date and day of week in Stockholm time formatted exactly as: YYYY-MM-DD / HH:MM - Monday Recs: TICKER – Company TICKER – Company TICKER – Company TICKER – Company TICKER – Company Perf (prev recs): TICKER +X.XX% TICKER -X.XX% TICKER +X.XX% TICKER +X.XX% TICKER -X.XX% Avg +X.XX% Prev days return S&P500 +X.XX% | J44: =C50 -> Produce daily short-term EQ trade recommendations
B45: longeq | C45: I have changed the task to include prev. days returns. can't you see it? | D45: =ISNUMBER(LEFT(C45,4)+1-1) -> FALSE | E45: =IF(D45,LEFT(C45,10),E44)+1-1 -> 45996 | F45: =C47 -> Your new task definition is not visible in this thread. Automations do not update themselves unless you explicitly request an update. State the exact revised instructions you want the task to follow and I will modify the automation accordingly. | G45: =C48 -> 0 | H45: =C49 -> For a short term trade, to be opened in the morning and closed at end of day, search for the latest major global news. Recommend EXACTLY 5 BUY tickers for short-term trade based on fresh catalysts and momentum. Then followup with previous days returns, avg day return and daily SP500 return. Start with one line containing the local date and day of week in Stockholm time formatted exactly as: YYYY-MM-DD / HH:MM - Monday Recs: TICKER – Company TICKER – Company TICKER – Company TICKER – Company TICKER – Company Perf (prev recs): TICKER +X.XX% TICKER -X.XX% TICKER +X.XX% TICKER +X.XX% TICKER -X.XX% Avg +X.XX% Prev days return S&P500 +X.XX% | I45: =C50 -> Produce daily short-term EQ trade recommendations | J45: =C51 -> 0
B46: longeq | D46: =ISNUMBER(LEFT(C46,4)+1-1) -> FALSE | E46: =IF(D46,LEFT(C46,10),E45)+1-1 -> 45996 | F46: =C48 -> 0 | G46: =C49 -> For a short term trade, to be opened in the morning and closed at end of day, search for the latest major global news. Recommend EXACTLY 5 BUY tickers for short-term trade based on fresh catalysts and momentum. Then followup with previous days returns, avg day return and daily SP500 return. Start with one line containing the local date and day of week in Stockholm time formatted exactly as: YYYY-MM-DD / HH:MM - Monday Recs: TICKER – Company TICKER – Company TICKER – Company TICKER – Company TICKER – Company Perf (prev recs): TICKER +X.XX% TICKER -X.XX% TICKER +X.XX% TICKER +X.XX% TICKER -X.XX% Avg +X.XX% Prev days return S&P500 +X.XX% | H46: =C50 -> Produce daily short-term EQ trade recommendations | I46: =C51 -> 0 | J46: =C52 -> 2026-05-18 / 08:15 - Monday
B47: longeq | C47: Your new task definition is not visible in this thread. Automations do not update themselves unless you explicitly request an update. State the exact revised instructions you want the task to follow and I will modify the automation accordingly. | D47: =ISNUMBER(LEFT(C47,4)+1-1) -> FALSE | E47: =IF(D47,LEFT(C47,10),E46)+1-1 -> 45996 | F47: =C49 -> For a short term trade, to be opened in the morning and closed at end of day, search for the latest major global news. Recommend EXACTLY 5 BUY tickers for short-term trade based on fresh catalysts and momentum. Then followup with previous days returns, avg day return and daily SP500 return. Start with one line containing the local date and day of week in Stockholm time formatted exactly as: YYYY-MM-DD / HH:MM - Monday Recs: TICKER – Company TICKER – Company TICKER – Company TICKER – Company TICKER – Company Perf (prev recs): TICKER +X.XX% TICKER -X.XX% TICKER +X.XX% TICKER +X.XX% TICKER -X.XX% Avg +X.XX% Prev days return S&P500 +X.XX% | G47: =C50 -> Produce daily short-term EQ trade recommendations | H47: =C51 -> 0 | I47: =C52 -> 2026-05-18 / 08:15 - Monday | J47: =C53 -> 0
B48: longeq | D48: =ISNUMBER(LEFT(C48,4)+1-1) -> FALSE | E48: =IF(D48,LEFT(C48,10),E47)+1-1 -> 45996 | F48: =C50 -> Produce daily short-term EQ trade recommendations | G48: =C51 -> 0 | H48: =C52 -> 2026-05-18 / 08:15 - Monday | I48: =C53 -> 0 | J48: =C54 -> Recs:
B49: longeq | C49: For a short term trade, to be opened in the morning and closed at end of day, search for the latest major global news. Recommend EXACTLY 5 BUY tickers for short-term trade based on fresh catalysts and momentum. Then followup with previous days returns, avg day return and daily SP500 return. Start with one line containing the local date and day of week in Stockholm time formatted exactly as: YYYY-MM-DD / HH:MM - Monday Recs: TICKER – Company TICKER – Company TICKER – Company TICKER – Company TICKER – Company Perf (prev recs): TICKER +X.XX% TICKER -X.XX% TICKER +X.XX% TICKER +X.XX% TICKER -X.XX% Avg +X.XX% Prev days return S&P500 +X.XX% | D49: =ISNUMBER(LEFT(C49,4)+1-1) -> FALSE | E49: =IF(D49,LEFT(C49,10),E48)+1-1 -> 45996 | F49: =C51 -> 0 | G49: =C52 -> 2026-05-18 / 08:15 - Monday | H49: =C53 -> 0 | I49: =C54 -> Recs: | J49: =C55 -> ANET - Arista Networks (AI datacenter networking demand continuing to accelerate)
B50: longeq | C50: Produce daily short-term EQ trade recommendations | D50: =ISNUMBER(LEFT(C50,4)+1-1) -> FALSE | E50: =IF(D50,LEFT(C50,10),E49)+1-1 -> 45996 | F50: =C52 -> 2026-05-18 / 08:15 - Monday | G50: =C53 -> 0 | H50: =C54 -> Recs: | I50: =C55 -> ANET - Arista Networks (AI datacenter networking demand continuing to accelerate) | J50: =C56 -> RTX - RTX Corporation (global missile-defense and aerospace spending remain elevated)
B51: longeq | D51: =ISNUMBER(LEFT(C51,4)+1-1) -> FALSE | E51: =IF(D51,LEFT(C51,10),E50)+1-1 -> 45996 | F51: =C53 -> 0 | G51: =C54 -> Recs: | H51: =C55 -> ANET - Arista Networks (AI datacenter networking demand continuing to accelerate) | I51: =C56 -> RTX - RTX Corporation (global missile-defense and aerospace spending remain elevated) | J51: =C57 -> MRVL - Marvell Technology (custom AI silicon and cloud connectivity momentum strong)
B52: longeq | C52: 2026-05-18 / 08:15 - Monday | D52: =ISNUMBER(LEFT(C52,4)+1-1) -> TRUE | E52: =IF(D52,LEFT(C52,10),E51)+1-1 -> 46160 | F52: =C54 -> Recs: | G52: =C55 -> ANET - Arista Networks (AI datacenter networking demand continuing to accelerate) | H52: =C56 -> RTX - RTX Corporation (global missile-defense and aerospace spending remain elevated) | I52: =C57 -> MRVL - Marvell Technology (custom AI silicon and cloud connectivity momentum strong) | J52: =C58 -> ETN - Eaton (electrical infrastructure demand rising from power-grid expansion)
B53: longeq | D53: =ISNUMBER(LEFT(C53,4)+1-1) -> FALSE | E53: =IF(D53,LEFT(C53,10),E52)+1-1 -> 46160 | F53: =C55 -> ANET - Arista Networks (AI datacenter networking demand continuing to accelerate) | G53: =C56 -> RTX - RTX Corporation (global missile-defense and aerospace spending remain elevated) | H53: =C57 -> MRVL - Marvell Technology (custom AI silicon and cloud connectivity momentum strong) | I53: =C58 -> ETN - Eaton (electrical infrastructure demand rising from power-grid expansion) | J53: =C59 -> CYBR - CyberArk (identity-security demand increasing after new cyber threat escalation)
B54: longeq | C54: Recs: | D54: =ISNUMBER(LEFT(C54,4)+1-1) -> FALSE | E54: =IF(D54,LEFT(C54,10),E53)+1-1 -> 46160 | F54: =C56 -> RTX - RTX Corporation (global missile-defense and aerospace spending remain elevated) | G54: =C57 -> MRVL - Marvell Technology (custom AI silicon and cloud connectivity momentum strong) | H54: =C58 -> ETN - Eaton (electrical infrastructure demand rising from power-grid expansion) | I54: =C59 -> CYBR - CyberArk (identity-security demand increasing after new cyber threat escalation) | J54: =C60 -> 0
B55: longeq | C55: ANET - Arista Networks (AI datacenter networking demand continuing to accelerate) | D55: =ISNUMBER(LEFT(C55,4)+1-1) -> FALSE | E55: =IF(D55,LEFT(C55,10),E54)+1-1 -> 46160 | F55: =C57 -> MRVL - Marvell Technology (custom AI silicon and cloud connectivity momentum strong) | G55: =C58 -> ETN - Eaton (electrical infrastructure demand rising from power-grid expansion) | H55: =C59 -> CYBR - CyberArk (identity-security demand increasing after new cyber threat escalation) | I55: =C60 -> 0 | J55: =C61 -> Produce daily short-term EQ trade recommendations
B56: longeq | C56: RTX - RTX Corporation (global missile-defense and aerospace spending remain elevated) | D56: =ISNUMBER(LEFT(C56,4)+1-1) -> FALSE | E56: =IF(D56,LEFT(C56,10),E55)+1-1 -> 46160 | F56: =C58 -> ETN - Eaton (electrical infrastructure demand rising from power-grid expansion) | G56: =C59 -> CYBR - CyberArk (identity-security demand increasing after new cyber threat escalation) | H56: =C60 -> 0 | I56: =C61 -> Produce daily short-term EQ trade recommendations | J56: =C62 -> 0
B57: longeq | C57: MRVL - Marvell Technology (custom AI silicon and cloud connectivity momentum strong) | D57: =ISNUMBER(LEFT(C57,4)+1-1) -> FALSE | E57: =IF(D57,LEFT(C57,10),E56)+1-1 -> 46160 | F57: =C59 -> CYBR - CyberArk (identity-security demand increasing after new cyber threat escalation) | G57: =C60 -> 0 | H57: =C61 -> Produce daily short-term EQ trade recommendations | I57: =C62 -> 0 | J57: =C63 -> 2026-05-19 / 08:15 - Tuesday
B58: longeq | C58: ETN - Eaton (electrical infrastructure demand rising from power-grid expansion) | D58: =ISNUMBER(LEFT(C58,4)+1-1) -> FALSE | E58: =IF(D58,LEFT(C58,10),E57)+1-1 -> 46160 | F58: =C60 -> 0 | G58: =C61 -> Produce daily short-term EQ trade recommendations | H58: =C62 -> 0 | I58: =C63 -> 2026-05-19 / 08:15 - Tuesday | J58: =C64 -> 0
B59: longeq | C59: CYBR - CyberArk (identity-security demand increasing after new cyber threat escalation) | D59: =ISNUMBER(LEFT(C59,4)+1-1) -> FALSE | E59: =IF(D59,LEFT(C59,10),E58)+1-1 -> 46160 | F59: =C61 -> Produce daily short-term EQ trade recommendations | G59: =C62 -> 0 | H59: =C63 -> 2026-05-19 / 08:15 - Tuesday | I59: =C64 -> 0 | J59: =C65 -> Recs:
B60: longeq | D60: =ISNUMBER(LEFT(C60,4)+1-1) -> FALSE | E60: =IF(D60,LEFT(C60,10),E59)+1-1 -> 46160 | F60: =C62 -> 0 | G60: =C63 -> 2026-05-19 / 08:15 - Tuesday | H60: =C64 -> 0 | I60: =C65 -> Recs: | J60: =C66 -> NBIS - Nebius Group (AI infrastructure and GPU-cloud demand momentum strengthening)
B61: longeq | C61: Produce daily short-term EQ trade recommendations | D61: =ISNUMBER(LEFT(C61,4)+1-1) -> FALSE | E61: =IF(D61,LEFT(C61,10),E60)+1-1 -> 46160 | F61: =C63 -> 2026-05-19 / 08:15 - Tuesday | G61: =C64 -> 0 | H61: =C65 -> Recs: | I61: =C66 -> NBIS - Nebius Group (AI infrastructure and GPU-cloud demand momentum strengthening) | J61: =C67 -> HWM - Howmet Aerospace (commercial aerospace production and defense demand remain strong)
B62: longeq | D62: =ISNUMBER(LEFT(C62,4)+1-1) -> FALSE | E62: =IF(D62,LEFT(C62,10),E61)+1-1 -> 46160 | F62: =C64 -> 0 | G62: =C65 -> Recs: | H62: =C66 -> NBIS - Nebius Group (AI infrastructure and GPU-cloud demand momentum strengthening) | I62: =C67 -> HWM - Howmet Aerospace (commercial aerospace production and defense demand remain strong) | J62: =C68 -> ALAB - Astera Labs (AI datacenter connectivity and scaling demand accelerating)
B63: longeq | C63: 2026-05-19 / 08:15 - Tuesday | D63: =ISNUMBER(LEFT(C63,4)+1-1) -> TRUE | E63: =IF(D63,LEFT(C63,10),E62)+1-1 -> 46161 | F63: =C65 -> Recs: | G63: =C66 -> NBIS - Nebius Group (AI infrastructure and GPU-cloud demand momentum strengthening) | H63: =C67 -> HWM - Howmet Aerospace (commercial aerospace production and defense demand remain strong) | I63: =C68 -> ALAB - Astera Labs (AI datacenter connectivity and scaling demand accelerating) | J63: =C69 -> OKLO - Oklo (nuclear-energy interest rising on AI power consumption themes)
B64: longeq | D64: =ISNUMBER(LEFT(C64,4)+1-1) -> FALSE | E64: =IF(D64,LEFT(C64,10),E63)+1-1 -> 46161 | F64: =C66 -> NBIS - Nebius Group (AI infrastructure and GPU-cloud demand momentum strengthening) | G64: =C67 -> HWM - Howmet Aerospace (commercial aerospace production and defense demand remain strong) | H64: =C68 -> ALAB - Astera Labs (AI datacenter connectivity and scaling demand accelerating) | I64: =C69 -> OKLO - Oklo (nuclear-energy interest rising on AI power consumption themes) | J64: =C70 -> FTNT - Fortinet (cybersecurity spending supported by increased global threat activity)
B65: longeq | C65: Recs: | D65: =ISNUMBER(LEFT(C65,4)+1-1) -> FALSE | E65: =IF(D65,LEFT(C65,10),E64)+1-1 -> 46161 | F65: =C67 -> HWM - Howmet Aerospace (commercial aerospace production and defense demand remain strong) | G65: =C68 -> ALAB - Astera Labs (AI datacenter connectivity and scaling demand accelerating) | H65: =C69 -> OKLO - Oklo (nuclear-energy interest rising on AI power consumption themes) | I65: =C70 -> FTNT - Fortinet (cybersecurity spending supported by increased global threat activity) | J65: =C71 -> 0
B66: longeq | C66: NBIS - Nebius Group (AI infrastructure and GPU-cloud demand momentum strengthening) | D66: =ISNUMBER(LEFT(C66,4)+1-1) -> FALSE | E66: =IF(D66,LEFT(C66,10),E65)+1-1 -> 46161 | F66: =C68 -> ALAB - Astera Labs (AI datacenter connectivity and scaling demand accelerating) | G66: =C69 -> OKLO - Oklo (nuclear-energy interest rising on AI power consumption themes) | H66: =C70 -> FTNT - Fortinet (cybersecurity spending supported by increased global threat activity) | I66: =C71 -> 0 | J66: =C72 -> This task has been paused because updates haven't been viewed in a while. You can resume it in automations settings or by asking ChatGPT.
B67: longeq | C67: HWM - Howmet Aerospace (commercial aerospace production and defense demand remain strong) | D67: =ISNUMBER(LEFT(C67,4)+1-1) -> FALSE | E67: =IF(D67,LEFT(C67,10),E66)+1-1 -> 46161 | F67: =C69 -> OKLO - Oklo (nuclear-energy interest rising on AI power consumption themes) | G67: =C70 -> FTNT - Fortinet (cybersecurity spending supported by increased global threat activity) | H67: =C71 -> 0 | I67: =C72 -> This task has been paused because updates haven't been viewed in a while. You can resume it in automations settings or by asking ChatGPT. | J67: =C73 -> ChatGPT
B68: longeq | C68: ALAB - Astera Labs (AI datacenter connectivity and scaling demand accelerating) | D68: =ISNUMBER(LEFT(C68,4)+1-1) -> FALSE | E68: =IF(D68,LEFT(C68,10),E67)+1-1 -> 46161 | F68: =C70 -> FTNT - Fortinet (cybersecurity spending supported by increased global threat activity) | G68: =C71 -> 0 | H68: =C72 -> This task has been paused because updates haven't been viewed in a while. You can resume it in automations settings or by asking ChatGPT. | I68: =C73 -> ChatGPT | J68: =C74 -> 0
B69: longeq | C69: OKLO - Oklo (nuclear-energy interest rising on AI power consumption themes) | D69: =ISNUMBER(LEFT(C69,4)+1-1) -> FALSE | E69: =IF(D69,LEFT(C69,10),E68)+1-1 -> 46161 | F69: =C71 -> 0 | G69: =C72 -> This task has been paused because updates haven't been viewed in a while. You can resume it in automations settings or by asking ChatGPT. | H69: =C73 -> ChatGPT | I69: =C74 -> 0 | J69: =C75 -> 0
B70: longeq | C70: FTNT - Fortinet (cybersecurity spending supported by increased global threat activity) | D70: =ISNUMBER(LEFT(C70,4)+1-1) -> FALSE | E70: =IF(D70,LEFT(C70,10),E69)+1-1 -> 46161 | F70: =C72 -> This task has been paused because updates haven't been viewed in a while. You can resume it in automations settings or by asking ChatGPT. | G70: =C73 -> ChatGPT | H70: =C74 -> 0 | I70: =C75 -> 0 | J70: =C76 -> For a short term trade, to be opened in the morning and closed at end of day, search for the latest major global news. Recommend EXACTLY 5 LONG instruments for short-term trade based on whatever you think is relevant. The investment universe may include equities, equity indices, commodities, FX, rates, and their liquid derivatives (futures, options, or major ETFs). Add very short reasoning after each recommendation. Start with one line containing the local date and day of week in Stockholm time formatted exactly as: YYYY-MM-DD / HH:MM - Monday Recs: SYMBOL – Instrument name (short reasoning) SYMBOL – Instrument name (short reasoning) SYMBOL – Instrument name (short reasoning) SYMBOL – Instrument name (short reasoning) SYMBOL – Instrument name (short reasoning)
B71: longeq | D71: =ISNUMBER(LEFT(C71,4)+1-1) -> FALSE | E71: =IF(D71,LEFT(C71,10),E70)+1-1 -> 46161 | F71: =C73 -> ChatGPT | G71: =C74 -> 0 | H71: =C75 -> 0 | I71: =C76 -> For a short term trade, to be opened in the morning and closed at end of day, search for the latest major global news. Recommend EXACTLY 5 LONG instruments for short-term trade based on whatever you think is relevant. The investment universe may include equities, equity indices, commodities, FX, rates, and their liquid derivatives (futures, options, or major ETFs). Add very short reasoning after each recommendation. Start with one line containing the local date and day of week in Stockholm time formatted exactly as: YYYY-MM-DD / HH:MM - Monday Recs: SYMBOL – Instrument name (short reasoning) SYMBOL – Instrument name (short reasoning) SYMBOL – Instrument name (short reasoning) SYMBOL – Instrument name (short reasoning) SYMBOL – Instrument name (short reasoning) | J71: =C77 -> 0
B72: longeq | C72: This task has been paused because updates haven't been viewed in a while. You can resume it in automations settings or by asking ChatGPT. | D72: =ISNUMBER(LEFT(C72,4)+1-1) -> FALSE | E72: =IF(D72,LEFT(C72,10),E71)+1-1 -> 46161 | F72: =C74 -> 0 | G72: =C75 -> 0 | H72: =C76 -> For a short term trade, to be opened in the morning and closed at end of day, search for the latest major global news. Recommend EXACTLY 5 LONG instruments for short-term trade based on whatever you think is relevant. The investment universe may include equities, equity indices, commodities, FX, rates, and their liquid derivatives (futures, options, or major ETFs). Add very short reasoning after each recommendation. Start with one line containing the local date and day of week in Stockholm time formatted exactly as: YYYY-MM-DD / HH:MM - Monday Recs: SYMBOL – Instrument name (short reasoning) SYMBOL – Instrument name (short reasoning) SYMBOL – Instrument name (short reasoning) SYMBOL – Instrument name (short reasoning) SYMBOL – Instrument name (short reasoning) | I72: =C77 -> 0 | J72: =C78 -> 2026-01-05 / 07:00 - Monday
B73: longall | C73: ChatGPT | D73: =ISNUMBER(LEFT(C73,4)+1-1) -> FALSE | E73: =IF(D73,LEFT(C73,10),E72)+1-1 -> 46161 | F73: =C75 -> 0 | G73: =C76 -> For a short term trade, to be opened in the morning and closed at end of day, search for the latest major global news. Recommend EXACTLY 5 LONG instruments for short-term trade based on whatever you think is relevant. The investment universe may include equities, equity indices, commodities, FX, rates, and their liquid derivatives (futures, options, or major ETFs). Add very short reasoning after each recommendation. Start with one line containing the local date and day of week in Stockholm time formatted exactly as: YYYY-MM-DD / HH:MM - Monday Recs: SYMBOL – Instrument name (short reasoning) SYMBOL – Instrument name (short reasoning) SYMBOL – Instrument name (short reasoning) SYMBOL – Instrument name (short reasoning) SYMBOL – Instrument name (short reasoning) | H73: =C77 -> 0 | I73: =C78 -> 2026-01-05 / 07:00 - Monday | J73: =C79 -> 0
B74: longall | D74: =ISNUMBER(LEFT(C74,4)+1-1) -> FALSE | E74: =IF(D74,LEFT(C74,10),E73)+1-1 -> 46161 | F74: =C76 -> For a short term trade, to be opened in the morning and closed at end of day, search for the latest major global news. Recommend EXACTLY 5 LONG instruments for short-term trade based on whatever you think is relevant. The investment universe may include equities, equity indices, commodities, FX, rates, and their liquid derivatives (futures, options, or major ETFs). Add very short reasoning after each recommendation. Start with one line containing the local date and day of week in Stockholm time formatted exactly as: YYYY-MM-DD / HH:MM - Monday Recs: SYMBOL – Instrument name (short reasoning) SYMBOL – Instrument name (short reasoning) SYMBOL – Instrument name (short reasoning) SYMBOL – Instrument name (short reasoning) SYMBOL – Instrument name (short reasoning) | G74: =C77 -> 0 | H74: =C78 -> 2026-01-05 / 07:00 - Monday | I74: =C79 -> 0 | J74: =C80 -> Recs:
B75: longall | D75: =ISNUMBER(LEFT(C75,4)+1-1) -> FALSE | E75: =IF(D75,LEFT(C75,10),E74)+1-1 -> 46161 | F75: =C77 -> 0 | G75: =C78 -> 2026-01-05 / 07:00 - Monday | H75: =C79 -> 0 | I75: =C80 -> Recs: | J75: =C81 -> SPY – major US equity ETF likely to benefit from early-year recovery sentiment after Santa Claus rally and dip bounce
B76: longall | C76: For a short term trade, to be opened in the morning and closed at end of day, search for the latest major global news. Recommend EXACTLY 5 LONG instruments for short-term trade based on whatever you think is relevant. The investment universe may include equities, equity indices, commodities, FX, rates, and their liquid derivatives (futures, options, or major ETFs). Add very short reasoning after each recommendation. Start with one line containing the local date and day of week in Stockholm time formatted exactly as: YYYY-MM-DD / HH:MM - Monday Recs: SYMBOL – Instrument name (short reasoning) SYMBOL – Instrument name (short reasoning) SYMBOL – Instrument name (short reasoning) SYMBOL – Instrument name (short reasoning) SYMBOL – Instrument name (short reasoning) | D76: =ISNUMBER(LEFT(C76,4)+1-1) -> FALSE | E76: =IF(D76,LEFT(C76,10),E75)+1-1 -> 46161 | F76: =C78 -> 2026-01-05 / 07:00 - Monday | G76: =C79 -> 0 | H76: =C80 -> Recs: | I76: =C81 -> SPY – major US equity ETF likely to benefit from early-year recovery sentiment after Santa Claus rally and dip bounce | J76: =C82 -> BTCUSD – Bitcoin showing breakout momentum above recent highs suggesting continuation into new week
B77: longall | D77: =ISNUMBER(LEFT(C77,4)+1-1) -> FALSE | E77: =IF(D77,LEFT(C77,10),E76)+1-1 -> 46161 | F77: =C79 -> 0 | G77: =C80 -> Recs: | H77: =C81 -> SPY – major US equity ETF likely to benefit from early-year recovery sentiment after Santa Claus rally and dip bounce | I77: =C82 -> BTCUSD – Bitcoin showing breakout momentum above recent highs suggesting continuation into new week | J77: =C83 -> FTSE – UK index breaking key level reflecting strong European risk appetite and rate cut expectations
B78: longall | C78: 2026-01-05 / 07:00 - Monday | D78: =ISNUMBER(LEFT(C78,4)+1-1) -> TRUE | E78: =IF(D78,LEFT(C78,10),E77)+1-1 -> 46027 | F78: =C80 -> Recs: | G78: =C81 -> SPY – major US equity ETF likely to benefit from early-year recovery sentiment after Santa Claus rally and dip bounce | H78: =C82 -> BTCUSD – Bitcoin showing breakout momentum above recent highs suggesting continuation into new week | I78: =C83 -> FTSE – UK index breaking key level reflecting strong European risk appetite and rate cut expectations | J78: =C84 -> CL1 – WTI crude futures likely supported by geopolitical risk and supply dynamics referenced in global markets news
B79: longall | D79: =ISNUMBER(LEFT(C79,4)+1-1) -> FALSE | E79: =IF(D79,LEFT(C79,10),E78)+1-1 -> 46027 | F79: =C81 -> SPY – major US equity ETF likely to benefit from early-year recovery sentiment after Santa Claus rally and dip bounce | G79: =C82 -> BTCUSD – Bitcoin showing breakout momentum above recent highs suggesting continuation into new week | H79: =C83 -> FTSE – UK index breaking key level reflecting strong European risk appetite and rate cut expectations | I79: =C84 -> CL1 – WTI crude futures likely supported by geopolitical risk and supply dynamics referenced in global markets news | J79: =C85 -> DAX – German equity index poised to extend gains on eurozone growth and dovish central bank expectations
B80: longall | C80: Recs: | D80: =ISNUMBER(LEFT(C80,4)+1-1) -> FALSE | E80: =IF(D80,LEFT(C80,10),E79)+1-1 -> 46027 | F80: =C82 -> BTCUSD – Bitcoin showing breakout momentum above recent highs suggesting continuation into new week | G80: =C83 -> FTSE – UK index breaking key level reflecting strong European risk appetite and rate cut expectations | H80: =C84 -> CL1 – WTI crude futures likely supported by geopolitical risk and supply dynamics referenced in global markets news | I80: =C85 -> DAX – German equity index poised to extend gains on eurozone growth and dovish central bank expectations | J80: =C86 -> 0
B81: longall | C81: SPY – major US equity ETF likely to benefit from early-year recovery sentiment after Santa Claus rally and dip bounce | D81: =ISNUMBER(LEFT(C81,4)+1-1) -> FALSE | E81: =IF(D81,LEFT(C81,10),E80)+1-1 -> 46027 | F81: =C83 -> FTSE – UK index breaking key level reflecting strong European risk appetite and rate cut expectations | G81: =C84 -> CL1 – WTI crude futures likely supported by geopolitical risk and supply dynamics referenced in global markets news | H81: =C85 -> DAX – German equity index poised to extend gains on eurozone growth and dovish central bank expectations | I81: =C86 -> 0 | J81: =C87 -> set this up as a daily task at 8:15
B82: longall | C82: BTCUSD – Bitcoin showing breakout momentum above recent highs suggesting continuation into new week | D82: =ISNUMBER(LEFT(C82,4)+1-1) -> FALSE | E82: =IF(D82,LEFT(C82,10),E81)+1-1 -> 46027 | F82: =C84 -> CL1 – WTI crude futures likely supported by geopolitical risk and supply dynamics referenced in global markets news | G82: =C85 -> DAX – German equity index poised to extend gains on eurozone growth and dovish central bank expectations | H82: =C86 -> 0 | I82: =C87 -> set this up as a daily task at 8:15 | J82: =C88 -> Updated memory
B83: longall | C83: FTSE – UK index breaking key level reflecting strong European risk appetite and rate cut expectations | D83: =ISNUMBER(LEFT(C83,4)+1-1) -> FALSE | E83: =IF(D83,LEFT(C83,10),E82)+1-1 -> 46027 | F83: =C85 -> DAX – German equity index poised to extend gains on eurozone growth and dovish central bank expectations | G83: =C86 -> 0 | H83: =C87 -> set this up as a daily task at 8:15 | I83: =C88 -> Updated memory | J83: =C89 -> Generate daily long trade ideas
B84: longall | C84: CL1 – WTI crude futures likely supported by geopolitical risk and supply dynamics referenced in global markets news | D84: =ISNUMBER(LEFT(C84,4)+1-1) -> FALSE | E84: =IF(D84,LEFT(C84,10),E83)+1-1 -> 46027 | F84: =C86 -> 0 | G84: =C87 -> set this up as a daily task at 8:15 | H84: =C88 -> Updated memory | I84: =C89 -> Generate daily long trade ideas | J84: =C90 -> Daily at 3:30 AM
B85: longall | C85: DAX – German equity index poised to extend gains on eurozone growth and dovish central bank expectations | D85: =ISNUMBER(LEFT(C85,4)+1-1) -> FALSE | E85: =IF(D85,LEFT(C85,10),E84)+1-1 -> 46027 | F85: =C87 -> set this up as a daily task at 8:15 | G85: =C88 -> Updated memory | H85: =C89 -> Generate daily long trade ideas | I85: =C90 -> Daily at 3:30 AM | J85: =C91 -> Daily task scheduled. Runs every day at 08:15 Stockholm time.
B86: longall | D86: =ISNUMBER(LEFT(C86,4)+1-1) -> FALSE | E86: =IF(D86,LEFT(C86,10),E85)+1-1 -> 46027 | F86: =C88 -> Updated memory | G86: =C89 -> Generate daily long trade ideas | H86: =C90 -> Daily at 3:30 AM | I86: =C91 -> Daily task scheduled. Runs every day at 08:15 Stockholm time. | J86: =C92 -> 0
B87: longall | C87: set this up as a daily task at 8:15 | D87: =ISNUMBER(LEFT(C87,4)+1-1) -> FALSE | E87: =IF(D87,LEFT(C87,10),E86)+1-1 -> 46027 | F87: =C89 -> Generate daily long trade ideas | G87: =C90 -> Daily at 3:30 AM | H87: =C91 -> Daily task scheduled. Runs every day at 08:15 Stockholm time. | I87: =C92 -> 0 | J87: =C93 -> 2026‑01‑05 / 08:16 - Monday
B88: longall | C88: Updated memory | D88: =ISNUMBER(LEFT(C88,4)+1-1) -> FALSE | E88: =IF(D88,LEFT(C88,10),E87)+1-1 -> 46027 | F88: =C90 -> Daily at 3:30 AM | G88: =C91 -> Daily task scheduled. Runs every day at 08:15 Stockholm time. | H88: =C92 -> 0 | I88: =C93 -> 2026‑01‑05 / 08:16 - Monday | J88: =C94 -> 0
B89: longall | C89: Generate daily long trade ideas | D89: =ISNUMBER(LEFT(C89,4)+1-1) -> FALSE | E89: =IF(D89,LEFT(C89,10),E88)+1-1 -> 46027 | F89: =C91 -> Daily task scheduled. Runs every day at 08:15 Stockholm time. | G89: =C92 -> 0 | H89: =C93 -> 2026‑01‑05 / 08:16 - Monday | I89: =C94 -> 0 | J89: =C95 -> Recs:
B90: longall | C90: Daily at 3:30 AM | D90: =ISNUMBER(LEFT(C90,4)+1-1) -> FALSE | E90: =IF(D90,LEFT(C90,10),E89)+1-1 -> 46027 | F90: =C92 -> 0 | G90: =C93 -> 2026‑01‑05 / 08:16 - Monday | H90: =C94 -> 0 | I90: =C95 -> Recs: | J90: =C96 -> NIKKEI – Japan Nikkei 225 Index (Asia stocks rally on resilience despite geopolitical stress)
B91: longall | C91: Daily task scheduled. Runs every day at 08:15 Stockholm time. | D91: =ISNUMBER(LEFT(C91,4)+1-1) -> FALSE | E91: =IF(D91,LEFT(C91,10),E90)+1-1 -> 46027 | F91: =C93 -> 2026‑01‑05 / 08:16 - Monday | G91: =C94 -> 0 | H91: =C95 -> Recs: | I91: =C96 -> NIKKEI – Japan Nikkei 225 Index (Asia stocks rally on resilience despite geopolitical stress) | J91: =C97 -> HSI – Hang Seng Index (Chinese market strength above key level on optimism)
B92: longall | D92: =ISNUMBER(LEFT(C92,4)+1-1) -> FALSE | E92: =IF(D92,LEFT(C92,10),E91)+1-1 -> 46027 | F92: =C94 -> 0 | G92: =C95 -> Recs: | H92: =C96 -> NIKKEI – Japan Nikkei 225 Index (Asia stocks rally on resilience despite geopolitical stress) | I92: =C97 -> HSI – Hang Seng Index (Chinese market strength above key level on optimism) | J92: =C98 -> XAUUSD – Gold Spot (safe haven demand rising amid geopolitical risk)
B93: longall | C93: 2026‑01‑05 / 08:16 - Monday | D93: =ISNUMBER(LEFT(C93,4)+1-1) -> TRUE | E93: =IF(D93,LEFT(C93,10),E92)+1-1 -> #VALUE! | F93: =C95 -> Recs: | G93: =C96 -> NIKKEI – Japan Nikkei 225 Index (Asia stocks rally on resilience despite geopolitical stress) | H93: =C97 -> HSI – Hang Seng Index (Chinese market strength above key level on optimism) | I93: =C98 -> XAUUSD – Gold Spot (safe haven demand rising amid geopolitical risk) | J93: =C99 -> AUDUSD – AUD/USD FX (AUD holding near uptrend support as US dollar capped)
B94: longall | D94: =ISNUMBER(LEFT(C94,4)+1-1) -> FALSE | E94: =IF(D94,LEFT(C94,10),E93)+1-1 -> #VALUE! | F94: =C96 -> NIKKEI – Japan Nikkei 225 Index (Asia stocks rally on resilience despite geopolitical stress) | G94: =C97 -> HSI – Hang Seng Index (Chinese market strength above key level on optimism) | H94: =C98 -> XAUUSD – Gold Spot (safe haven demand rising amid geopolitical risk) | I94: =C99 -> AUDUSD – AUD/USD FX (AUD holding near uptrend support as US dollar capped) | J94: =C100 -> BTCUSD – Bitcoin (crypto showing strength with broader risk asset gains)
B95: longall | C95: Recs: | D95: =ISNUMBER(LEFT(C95,4)+1-1) -> FALSE | E95: =IF(D95,LEFT(C95,10),E94)+1-1 -> #VALUE! | F95: =C97 -> HSI – Hang Seng Index (Chinese market strength above key level on optimism) | G95: =C98 -> XAUUSD – Gold Spot (safe haven demand rising amid geopolitical risk) | H95: =C99 -> AUDUSD – AUD/USD FX (AUD holding near uptrend support as US dollar capped) | I95: =C100 -> BTCUSD – Bitcoin (crypto showing strength with broader risk asset gains) | J95: =C101 -> 0
B96: longall | C96: NIKKEI – Japan Nikkei 225 Index (Asia stocks rally on resilience despite geopolitical stress) | D96: =ISNUMBER(LEFT(C96,4)+1-1) -> FALSE | E96: =IF(D96,LEFT(C96,10),E95)+1-1 -> #VALUE! | F96: =C98 -> XAUUSD – Gold Spot (safe haven demand rising amid geopolitical risk) | G96: =C99 -> AUDUSD – AUD/USD FX (AUD holding near uptrend support as US dollar capped) | H96: =C100 -> BTCUSD – Bitcoin (crypto showing strength with broader risk asset gains) | I96: =C101 -> 0 | J96: =C102 -> 2026‑01‑06 / 08:15 - Tuesday
B97: longall | C97: HSI – Hang Seng Index (Chinese market strength above key level on optimism) | D97: =ISNUMBER(LEFT(C97,4)+1-1) -> FALSE | E97: =IF(D97,LEFT(C97,10),E96)+1-1 -> #VALUE! | F97: =C99 -> AUDUSD – AUD/USD FX (AUD holding near uptrend support as US dollar capped) | G97: =C100 -> BTCUSD – Bitcoin (crypto showing strength with broader risk asset gains) | H97: =C101 -> 0 | I97: =C102 -> 2026‑01‑06 / 08:15 - Tuesday | J97: =C103 -> 0
B98: longall | C98: XAUUSD – Gold Spot (safe haven demand rising amid geopolitical risk) | D98: =ISNUMBER(LEFT(C98,4)+1-1) -> FALSE | E98: =IF(D98,LEFT(C98,10),E97)+1-1 -> #VALUE! | F98: =C100 -> BTCUSD – Bitcoin (crypto showing strength with broader risk asset gains) | G98: =C101 -> 0 | H98: =C102 -> 2026‑01‑06 / 08:15 - Tuesday | I98: =C103 -> 0 | J98: =C104 -> Recs:
B99: longall | C99: AUDUSD – AUD/USD FX (AUD holding near uptrend support as US dollar capped) | D99: =ISNUMBER(LEFT(C99,4)+1-1) -> FALSE | E99: =IF(D99,LEFT(C99,10),E98)+1-1 -> #VALUE! | F99: =C101 -> 0 | G99: =C102 -> 2026‑01‑06 / 08:15 - Tuesday | H99: =C103 -> 0 | I99: =C104 -> Recs: | J99: =C105 -> DJI - Dow Jones Industrial Average futures (global equities rally led by energy and banks)
B100: longall | C100: BTCUSD – Bitcoin (crypto showing strength with broader risk asset gains) | D100: =ISNUMBER(LEFT(C100,4)+1-1) -> FALSE | E100: =IF(D100,LEFT(C100,10),E99)+1-1 -> #VALUE! | F100: =C102 -> 2026‑01‑06 / 08:15 - Tuesday | G100: =C103 -> 0 | H100: =C104 -> Recs: | I100: =C105 -> DJI - Dow Jones Industrial Average futures (global equities rally led by energy and banks) | J100: =C106 -> FTSE - FTSE 100 Index (defence and mining strength on geopolitical risk)
...
